{
	"data": [{
		"message": "---------------------------------------- \nFor this NETBOX is a starter- or connection cable required.  \nPlease select it in the area NETLINE!",
		"facility": "GF::afml",
		"level": "Notice",
		"timeStamp": "2019-02-04T20:51:54.685Z"
	}, {
		"message": "---------------------------------------- \nFor this NETBOX is a starter- or connection cable required.  \nPlease select it in the area NETLINE!",
		"facility": "GF::afml",
		"level": "Notice",
		"timeStamp": "2019-02-05T20:51:58.357Z"
	}, {
		"message": "\"CHASSIS\" has not been declared as a property alias in relation \"000000000000004839\" of \"@_xxxpb\".",
		"facility": "GF::eai:eproduct",
		"level": "Debug",
		"timeStamp": "2019-02-05T20:52:05.057Z"
	}, {
		"message": "\"STROMAUSGANG\" has not been declared as a property alias in relation \"000000000000004839\" of \"@_xxxpb\".",
		"facility": "GF::eai:eproduct",
		"level": "Debug",
		"timeStamp": "2019-02-05T20:52:05.057Z"
	}, {
		"message": "\"STROMEINGANG\" has not been declared as a property alias in relation \"000000000000004839\" of \"@_xxxpb\".",
		"facility": "GF::eai:eproduct",
		"level": "Debug",
		"timeStamp": "2019-02-05T20:52:05.057Z"
	}, {
		"message": "\"QUERSCHNITT\" has not been declared as a property alias in relation \"000000000000004839\" of \"@_xxxpb\".",
		"facility": "GF::eai:eproduct",
		"level": "Debug",
		"timeStamp": "2019-02-05T20:52:05.057Z"
	}, {
		"message": "\"INT_EXT\" has not been declared as a property alias in relation \"000000000000004839\" of \"@_xxxpb\".",
		"facility": "GF::eai:eproduct",
		"level": "Debug",
		"timeStamp": "2019-02-05T20:52:05.057Z"
	}, {
		"message": "\"PB_VAR\" has not been declared as a property alias in relation \"000000000000004839\" of \"@_xxxpb\".",
		"facility": "GF::eai:eproduct",
		"level": "Debug",
		"timeStamp": "2019-02-05T20:52:05.057Z"
	}, {
		"message": "\"CHASSIS\" has not been declared as a property alias in relation \"000000000000004851\" of \"@_xxxpb\".",
		"facility": "GF::eai:eproduct",
		"level": "Debug",
		"timeStamp": "2019-02-05T20:52:05.057Z"
	}, {
		"message": "\"STROMAUSGANG\" has not been declared as a property alias in relation \"000000000000004851\" of \"@_xxxpb\".",
		"facility": "GF::eai:eproduct",
		"level": "Debug",
		"timeStamp": "2019-02-05T20:52:05.057Z"
	}, {
		"message": "\"STROMEINGANG\" has not been declared as a property alias in relation \"000000000000004851\" of \"@_xxxpb\".",
		"facility": "GF::eai:eproduct",
		"level": "Debug",
		"timeStamp": "2019-02-05T20:52:05.057Z"
	}, {
		"message": "\"QUERSCHNITT\" has not been declared as a property alias in relation \"000000000000004851\" of \"@_xxxpb\".",
		"facility": "GF::eai:eproduct",
		"level": "Debug",
		"timeStamp": "2019-02-05T20:52:05.057Z"
	}, {
		"message": "\"INT_EXT\" has not been declared as a property alias in relation \"000000000000004851\" of \"@_xxxpb\".",
		"facility": "GF::eai:eproduct",
		"level": "Debug",
		"timeStamp": "2019-02-05T20:52:05.057Z"
	}, {
		"message": "\"CHASSIS\" has not been declared as a property alias in relation \"000000000000004861\" of \"@_xxxpb\".",
		"facility": "GF::eai:eproduct",
		"level": "Debug",
		"timeStamp": "2019-02-05T20:52:05.057Z"
	}, {
		"message": "\"STROMAUSGANG\" has not been declared as a property alias in relation \"000000000000004861\" of \"@_xxxpb\".",
		"facility": "GF::eai:eproduct",
		"level": "Debug",
		"timeStamp": "2019-02-05T20:52:05.057Z"
	}, {
		"message": "\"STROMEINGANG\" has not been declared as a property alias in relation \"000000000000004861\" of \"@_xxxpb\".",
		"facility": "GF::eai:eproduct",
		"level": "Debug",
		"timeStamp": "2019-02-05T20:52:05.057Z"
	}, {
		"message": "\"QUERSCHNITT\" has not been declared as a property alias in relation \"000000000000004861\" of \"@_xxxpb\".",
		"facility": "GF::eai:eproduct",
		"level": "Debug",
		"timeStamp": "2019-02-05T20:52:05.057Z"
	}, {
		"message": "\"INT_EXT\" has not been declared as a property alias in relation \"000000000000004861\" of \"@_xxxpb\".",
		"facility": "GF::eai:eproduct",
		"level": "Debug",
		"timeStamp": "2019-02-05T20:52:05.057Z"
	}, {
		"message": "\"PB_VAR\" has not been declared as a property alias in relation \"000000000000004861\" of \"@_xxxpb\".",
		"facility": "GF::eai:eproduct",
		"level": "Debug",
		"timeStamp": "2019-02-05T20:52:05.057Z"
	}, {
		"message": "\"CHASSIS\" has not been declared as a property alias in relation \"000000000000004863\" of \"@_xxxpb\".",
		"facility": "GF::eai:eproduct",
		"level": "Debug",
		"timeStamp": "2019-02-05T20:52:05.057Z"
	}, {
		"message": "\"STROMAUSGANG\" has not been declared as a property alias in relation \"000000000000004863\" of \"@_xxxpb\".",
		"facility": "GF::eai:eproduct",
		"level": "Debug",
		"timeStamp": "2019-02-05T20:52:05.058Z"
	}, {
		"message": "\"STROMEINGANG\" has not been declared as a property alias in relation \"000000000000004863\" of \"@_xxxpb\".",
		"facility": "GF::eai:eproduct",
		"level": "Debug",
		"timeStamp": "2019-02-05T20:52:05.058Z"
	}, {
		"message": "\"QUERSCHNITT\" has not been declared as a property alias in relation \"000000000000004863\" of \"@_xxxpb\".",
		"facility": "GF::eai:eproduct",
		"level": "Debug",
		"timeStamp": "2019-02-05T20:52:05.058Z"
	}, {
		"message": "\"INT_EXT\" has not been declared as a property alias in relation \"000000000000004863\" of \"@_xxxpb\".",
		"facility": "GF::eai:eproduct",
		"level": "Debug",
		"timeStamp": "2019-02-05T20:52:05.058Z"
	}, {
		"message": "\"CHASSIS\" has not been declared as a property alias in relation \"000000000000004862\" of \"@_xxxpb\".",
		"facility": "GF::eai:eproduct",
		"level": "Debug",
		"timeStamp": "2019-02-05T20:52:05.058Z"
	}, {
		"message": "\"STROMAUSGANG\" has not been declared as a property alias in relation \"000000000000004862\" of \"@_xxxpb\".",
		"facility": "GF::eai:eproduct",
		"level": "Debug",
		"timeStamp": "2019-02-05T20:52:05.058Z"
	}, {
		"message": "\"STROMEINGANG\" has not been declared as a property alias in relation \"000000000000004862\" of \"@_xxxpb\".",
		"facility": "GF::eai:eproduct",
		"level": "Debug",
		"timeStamp": "2019-02-05T20:52:05.058Z"
	}, {
		"message": "\"QUERSCHNITT\" has not been declared as a property alias in relation \"000000000000004862\" of \"@_xxxpb\".",
		"facility": "GF::eai:eproduct",
		"level": "Debug",
		"timeStamp": "2019-02-05T20:52:05.058Z"
	}, {
		"message": "\"INT_EXT\" has not been declared as a property alias in relation \"000000000000004862\" of \"@_xxxpb\".",
		"facility": "GF::eai:eproduct",
		"level": "Debug",
		"timeStamp": "2019-02-05T20:52:05.058Z"
	}, {
		"message": "\"CHASSIS\" has not been declared as a property alias in relation \"000000000000008692\" of \"@_xxxpb\".",
		"facility": "GF::eai:eproduct",
		"level": "Debug",
		"timeStamp": "2019-02-05T20:52:05.058Z"
	}, {
		"message": "\"STROMAUSGANG\" has not been declared as a property alias in relation \"000000000000008692\" of \"@_xxxpb\".",
		"facility": "GF::eai:eproduct",
		"level": "Debug",
		"timeStamp": "2019-02-05T20:52:05.058Z"
	}, {
		"message": "\"STROMEINGANG\" has not been declared as a property alias in relation \"000000000000008692\" of \"@_xxxpb\".",
		"facility": "GF::eai:eproduct",
		"level": "Debug",
		"timeStamp": "2019-02-05T20:52:05.058Z"
	}, {
		"message": "\"QUERSCHNITT\" has not been declared as a property alias in relation \"000000000000008692\" of \"@_xxxpb\".",
		"facility": "GF::eai:eproduct",
		"level": "Debug",
		"timeStamp": "2019-02-05T20:52:05.058Z"
	}, {
		"message": "\"INT_EXT\" has not been declared as a property alias in relation \"000000000000008692\" of \"@_xxxpb\".",
		"facility": "GF::eai:eproduct",
		"level": "Debug",
		"timeStamp": "2019-02-05T20:52:05.058Z"
	}, {
		"message": "\"CHASSIS\" has not been declared as a property alias in relation \"000000000000008694\" of \"@_xxxpb\".",
		"facility": "GF::eai:eproduct",
		"level": "Debug",
		"timeStamp": "2019-02-05T20:52:05.058Z"
	}, {
		"message": "\"STROMAUSGANG\" has not been declared as a property alias in relation \"000000000000008694\" of \"@_xxxpb\".",
		"facility": "GF::eai:eproduct",
		"level": "Debug",
		"timeStamp": "2019-02-05T20:52:05.058Z"
	}, {
		"message": "\"STROMEINGANG\" has not been declared as a property alias in relation \"000000000000008694\" of \"@_xxxpb\".",
		"facility": "GF::eai:eproduct",
		"level": "Debug",
		"timeStamp": "2019-02-05T20:52:05.058Z"
	}, {
		"message": "\"QUERSCHNITT\" has not been declared as a property alias in relation \"000000000000008694\" of \"@_xxxpb\".",
		"facility": "GF::eai:eproduct",
		"level": "Debug",
		"timeStamp": "2019-02-05T20:52:05.058Z"
	}, {
		"message": "\"INT_EXT\" has not been declared as a property alias in relation \"000000000000008694\" of \"@_xxxpb\".",
		"facility": "GF::eai:eproduct",
		"level": "Debug",
		"timeStamp": "2019-02-05T20:52:05.058Z"
	}, {
		"message": "\"CHASSIS\" has not been declared as a property alias in relation \"000000000000008696\" of \"@_xxxpb\".",
		"facility": "GF::eai:eproduct",
		"level": "Debug",
		"timeStamp": "2019-02-05T20:52:05.058Z"
	}, {
		"message": "\"STROMAUSGANG\" has not been declared as a property alias in relation \"000000000000008696\" of \"@_xxxpb\".",
		"facility": "GF::eai:eproduct",
		"level": "Debug",
		"timeStamp": "2019-02-05T20:52:05.058Z"
	}, {
		"message": "\"STROMEINGANG\" has not been declared as a property alias in relation \"000000000000008696\" of \"@_xxxpb\".",
		"facility": "GF::eai:eproduct",
		"level": "Debug",
		"timeStamp": "2019-02-05T20:52:05.058Z"
	}, {
		"message": "\"QUERSCHNITT\" has not been declared as a property alias in relation \"000000000000008696\" of \"@_xxxpb\".",
		"facility": "GF::eai:eproduct",
		"level": "Debug",
		"timeStamp": "2019-02-05T20:52:05.058Z"
	}, {
		"message": "\"INT_EXT\" has not been declared as a property alias in relation \"000000000000008696\" of \"@_xxxpb\".",
		"facility": "GF::eai:eproduct",
		"level": "Debug",
		"timeStamp": "2019-02-05T20:52:05.058Z"
	}, {
		"message": "\"CHASSIS\" has not been declared as a property alias in relation \"000000000000008698\" of \"@_xxxpb\".",
		"facility": "GF::eai:eproduct",
		"level": "Debug",
		"timeStamp": "2019-02-05T20:52:05.058Z"
	}, {
		"message": "\"QUERSCHNITT\" has not been declared as a property alias in relation \"000000000000008698\" of \"@_xxxpb\".",
		"facility": "GF::eai:eproduct",
		"level": "Debug",
		"timeStamp": "2019-02-05T20:52:05.058Z"
	}, {
		"message": "\"INT_EXT\" has not been declared as a property alias in relation \"000000000000008698\" of \"@_xxxpb\".",
		"facility": "GF::eai:eproduct",
		"level": "Debug",
		"timeStamp": "2019-02-05T20:52:05.058Z"
	}, {
		"message": "\"CHASSIS\" has not been declared as a property alias in relation \"000000000000010133\" of \"@_xxxpb\".",
		"facility": "GF::eai:eproduct",
		"level": "Debug",
		"timeStamp": "2019-02-05T20:52:05.058Z"
	}, {
		"message": "\"QUERSCHNITT\" has not been declared as a property alias in relation \"000000000000010133\" of \"@_xxxpb\".",
		"facility": "GF::eai:eproduct",
		"level": "Debug",
		"timeStamp": "2019-02-05T20:52:05.058Z"
	}, {
		"message": "\"INT_EXT\" has not been declared as a property alias in relation \"000000000000010133\" of \"@_xxxpb\".",
		"facility": "GF::eai:eproduct",
		"level": "Debug",
		"timeStamp": "2019-02-05T20:52:05.058Z"
	}, {
		"message": "\"CHASSIS\" has not been declared as a property alias in relation \"000000000000010134\" of \"@_xxxpb\".",
		"facility": "GF::eai:eproduct",
		"level": "Debug",
		"timeStamp": "2019-02-05T20:52:05.058Z"
	}, {
		"message": "\"QUERSCHNITT\" has not been declared as a property alias in relation \"000000000000010134\" of \"@_xxxpb\".",
		"facility": "GF::eai:eproduct",
		"level": "Debug",
		"timeStamp": "2019-02-05T20:52:05.058Z"
	}, {
		"message": "\"INT_EXT\" has not been declared as a property alias in relation \"000000000000010134\" of \"@_xxxpb\".",
		"facility": "GF::eai:eproduct",
		"level": "Debug",
		"timeStamp": "2019-02-05T20:52:05.058Z"
	}, {
		"message": "\"CHASSIS\" has not been declared as a property alias in relation \"000000000000010136\" of \"@_xxxpb\".",
		"facility": "GF::eai:eproduct",
		"level": "Debug",
		"timeStamp": "2019-02-05T20:52:05.058Z"
	}, {
		"message": "\"QUERSCHNITT\" has not been declared as a property alias in relation \"000000000000010136\" of \"@_xxxpb\".",
		"facility": "GF::eai:eproduct",
		"level": "Debug",
		"timeStamp": "2019-02-05T20:52:05.058Z"
	}, {
		"message": "\"INT_EXT\" has not been declared as a property alias in relation \"000000000000010136\" of \"@_xxxpb\".",
		"facility": "GF::eai:eproduct",
		"level": "Debug",
		"timeStamp": "2019-02-05T20:52:05.058Z"
	}, {
		"message": "\"PB_VAR\" has not been declared as a property alias in relation \"000000000000010136\" of \"@_xxxpb\".",
		"facility": "GF::eai:eproduct",
		"level": "Debug",
		"timeStamp": "2019-02-05T20:52:05.058Z"
	}, {
		"message": "\"CHASSIS\" has not been declared as a property alias in relation \"000000000000010138\" of \"@_xxxpb\".",
		"facility": "GF::eai:eproduct",
		"level": "Debug",
		"timeStamp": "2019-02-05T20:52:05.058Z"
	}, {
		"message": "\"QUERSCHNITT\" has not been declared as a property alias in relation \"000000000000010138\" of \"@_xxxpb\".",
		"facility": "GF::eai:eproduct",
		"level": "Debug",
		"timeStamp": "2019-02-05T20:52:05.058Z"
	}, {
		"message": "\"INT_EXT\" has not been declared as a property alias in relation \"000000000000010138\" of \"@_xxxpb\".",
		"facility": "GF::eai:eproduct",
		"level": "Debug",
		"timeStamp": "2019-02-05T20:52:05.058Z"
	}, {
		"message": "\"CHASSIS\" has not been declared as a property alias in relation \"000000000000010140\" of \"@_xxxpb\".",
		"facility": "GF::eai:eproduct",
		"level": "Debug",
		"timeStamp": "2019-02-05T20:52:05.058Z"
	}, {
		"message": "\"QUERSCHNITT\" has not been declared as a property alias in relation \"000000000000010140\" of \"@_xxxpb\".",
		"facility": "GF::eai:eproduct",
		"level": "Debug",
		"timeStamp": "2019-02-05T20:52:05.058Z"
	}, {
		"message": "\"INT_EXT\" has not been declared as a property alias in relation \"000000000000010140\" of \"@_xxxpb\".",
		"facility": "GF::eai:eproduct",
		"level": "Debug",
		"timeStamp": "2019-02-05T20:52:05.058Z"
	}, {
		"message": "\"CHASSIS\" has not been declared as a property alias in relation \"000000000000010135\" of \"@_xxxpb\".",
		"facility": "GF::eai:eproduct",
		"level": "Debug",
		"timeStamp": "2019-02-05T20:52:05.058Z"
	}, {
		"message": "\"QUERSCHNITT\" has not been declared as a property alias in relation \"000000000000010135\" of \"@_xxxpb\".",
		"facility": "GF::eai:eproduct",
		"level": "Debug",
		"timeStamp": "2019-02-05T20:52:05.058Z"
	}, {
		"message": "\"INT_EXT\" has not been declared as a property alias in relation \"000000000000010135\" of \"@_xxxpb\".",
		"facility": "GF::eai:eproduct",
		"level": "Debug",
		"timeStamp": "2019-02-05T20:52:05.058Z"
	}, {
		"message": "\"CHASSIS\" has not been declared as a property alias in relation \"000000000000010137\" of \"@_xxxpb\".",
		"facility": "GF::eai:eproduct",
		"level": "Debug",
		"timeStamp": "2019-02-05T20:52:05.058Z"
	}, {
		"message": "\"QUERSCHNITT\" has not been declared as a property alias in relation \"000000000000010137\" of \"@_xxxpb\".",
		"facility": "GF::eai:eproduct",
		"level": "Debug",
		"timeStamp": "2019-02-05T20:52:05.058Z"
	}, {
		"message": "\"INT_EXT\" has not been declared as a property alias in relation \"000000000000010137\" of \"@_xxxpb\".",
		"facility": "GF::eai:eproduct",
		"level": "Debug",
		"timeStamp": "2019-02-05T20:52:05.058Z"
	}, {
		"message": "\"CHASSIS\" has not been declared as a property alias in relation \"000000000000010139\" of \"@_xxxpb\".",
		"facility": "GF::eai:eproduct",
		"level": "Debug",
		"timeStamp": "2019-02-05T20:52:05.058Z"
	}, {
		"message": "\"QUERSCHNITT\" has not been declared as a property alias in relation \"000000000000010139\" of \"@_xxxpb\".",
		"facility": "GF::eai:eproduct",
		"level": "Debug",
		"timeStamp": "2019-02-05T20:52:05.058Z"
	}, {
		"message": "\"INT_EXT\" has not been declared as a property alias in relation \"000000000000010139\" of \"@_xxxpb\".",
		"facility": "GF::eai:eproduct",
		"level": "Debug",
		"timeStamp": "2019-02-05T20:52:05.058Z"
	}, {
		"message": "\"CHASSIS\" has not been declared as a property alias in relation \"000000000000010141\" of \"@_xxxpb\".",
		"facility": "GF::eai:eproduct",
		"level": "Debug",
		"timeStamp": "2019-02-05T20:52:05.058Z"
	}, {
		"message": "\"QUERSCHNITT\" has not been declared as a property alias in relation \"000000000000010141\" of \"@_xxxpb\".",
		"facility": "GF::eai:eproduct",
		"level": "Debug",
		"timeStamp": "2019-02-05T20:52:05.058Z"
	}, {
		"message": "\"INT_EXT\" has not been declared as a property alias in relation \"000000000000010141\" of \"@_xxxpb\".",
		"facility": "GF::eai:eproduct",
		"level": "Debug",
		"timeStamp": "2019-02-05T20:52:05.058Z"
	}, {
		"message": "\"QUERSCHNITT\" has not been declared as a property alias in relation \"000000000000006726\" of \"@_xxxpb\".",
		"facility": "GF::eai:eproduct",
		"level": "Debug",
		"timeStamp": "2019-02-05T20:52:05.058Z"
	}, {
		"message": "\"STROMAUSGANG\" has not been declared as a property alias in relation \"000000000000006726\" of \"@_xxxpb\".",
		"facility": "GF::eai:eproduct",
		"level": "Debug",
		"timeStamp": "2019-02-05T20:52:05.058Z"
	}, {
		"message": "\"CHASSIS\" has not been declared as a property alias in relation \"000000000000006726\" of \"@_xxxpb\".",
		"facility": "GF::eai:eproduct",
		"level": "Debug",
		"timeStamp": "2019-02-05T20:52:05.058Z"
	}, {
		"message": "\"CHASSIS\" has not been declared as a property alias in relation \"000000000000006728\" of \"@_xxxpb\".",
		"facility": "GF::eai:eproduct",
		"level": "Debug",
		"timeStamp": "2019-02-05T20:52:05.058Z"
	}, {
		"message": "\"QUERSCHNITT\" has not been declared as a property alias in relation \"000000000000006728\" of \"@_xxxpb\".",
		"facility": "GF::eai:eproduct",
		"level": "Debug",
		"timeStamp": "2019-02-05T20:52:05.058Z"
	}, {
		"message": "\"STROMAUSGANG\" has not been declared as a property alias in relation \"000000000000006728\" of \"@_xxxpb\".",
		"facility": "GF::eai:eproduct",
		"level": "Debug",
		"timeStamp": "2019-02-05T20:52:05.058Z"
	}, {
		"message": "\"CHASSIS\" has not been declared as a property alias in relation \"000000000000006730\" of \"@_xxxpb\".",
		"facility": "GF::eai:eproduct",
		"level": "Debug",
		"timeStamp": "2019-02-05T20:52:05.058Z"
	}, {
		"message": "\"QUERSCHNITT\" has not been declared as a property alias in relation \"000000000000006730\" of \"@_xxxpb\".",
		"facility": "GF::eai:eproduct",
		"level": "Debug",
		"timeStamp": "2019-02-05T20:52:05.058Z"
	}, {
		"message": "\"STROMAUSGANG\" has not been declared as a property alias in relation \"000000000000006730\" of \"@_xxxpb\".",
		"facility": "GF::eai:eproduct",
		"level": "Debug",
		"timeStamp": "2019-02-05T20:52:05.058Z"
	}, {
		"message": "\"CHASSIS\" has not been declared as a property alias in relation \"000000000000006727\" of \"@_xxxpb\".",
		"facility": "GF::eai:eproduct",
		"level": "Debug",
		"timeStamp": "2019-02-05T20:52:05.058Z"
	}, {
		"message": "\"QUERSCHNITT\" has not been declared as a property alias in relation \"000000000000006727\" of \"@_xxxpb\".",
		"facility": "GF::eai:eproduct",
		"level": "Debug",
		"timeStamp": "2019-02-05T20:52:05.058Z"
	}, {
		"message": "\"STROMAUSGANG\" has not been declared as a property alias in relation \"000000000000006727\" of \"@_xxxpb\".",
		"facility": "GF::eai:eproduct",
		"level": "Debug",
		"timeStamp": "2019-02-05T20:52:05.058Z"
	}, {
		"message": "\"CHASSIS\" has not been declared as a property alias in relation \"000000000000006729\" of \"@_xxxpb\".",
		"facility": "GF::eai:eproduct",
		"level": "Debug",
		"timeStamp": "2019-02-05T20:52:05.058Z"
	}, {
		"message": "\"QUERSCHNITT\" has not been declared as a property alias in relation \"000000000000006729\" of \"@_xxxpb\".",
		"facility": "GF::eai:eproduct",
		"level": "Debug",
		"timeStamp": "2019-02-05T20:52:05.058Z"
	}, {
		"message": "\"STROMAUSGANG\" has not been declared as a property alias in relation \"000000000000006729\" of \"@_xxxpb\".",
		"facility": "GF::eai:eproduct",
		"level": "Debug",
		"timeStamp": "2019-02-05T20:52:05.058Z"
	}, {
		"message": "\"CHASSIS\" has not been declared as a property alias in relation \"000000000000008693\" of \"@_xxxpb\".",
		"facility": "GF::eai:eproduct",
		"level": "Debug",
		"timeStamp": "2019-02-05T20:52:05.058Z"
	}, {
		"message": "\"QUERSCHNITT\" has not been declared as a property alias in relation \"000000000000008693\" of \"@_xxxpb\".",
		"facility": "GF::eai:eproduct",
		"level": "Debug",
		"timeStamp": "2019-02-05T20:52:05.058Z"
	}, {
		"message": "\"STROMAUSGANG\" has not been declared as a property alias in relation \"000000000000008693\" of \"@_xxxpb\".",
		"facility": "GF::eai:eproduct",
		"level": "Debug",
		"timeStamp": "2019-02-05T20:52:05.058Z"
	}, {
		"message": "\"CHASSIS\" has not been declared as a property alias in relation \"000000000000008695\" of \"@_xxxpb\".",
		"facility": "GF::eai:eproduct",
		"level": "Debug",
		"timeStamp": "2019-02-05T20:52:05.058Z"
	}, {
		"message": "\"QUERSCHNITT\" has not been declared as a property alias in relation \"000000000000008695\" of \"@_xxxpb\".",
		"facility": "GF::eai:eproduct",
		"level": "Debug",
		"timeStamp": "2019-02-05T20:52:05.058Z"
	}, {
		"message": "\"STROMAUSGANG\" has not been declared as a property alias in relation \"000000000000008695\" of \"@_xxxpb\".",
		"facility": "GF::eai:eproduct",
		"level": "Debug",
		"timeStamp": "2019-02-05T20:52:05.058Z"
	}, {
		"message": "\"CHASSIS\" has not been declared as a property alias in relation \"000000000000008697\" of \"@_xxxpb\".",
		"facility": "GF::eai:eproduct",
		"level": "Debug",
		"timeStamp": "2019-02-05T20:52:05.058Z"
	}, {
		"message": "\"QUERSCHNITT\" has not been declared as a property alias in relation \"000000000000008697\" of \"@_xxxpb\".",
		"facility": "GF::eai:eproduct",
		"level": "Debug",
		"timeStamp": "2019-02-05T20:52:05.058Z"
	}, {
		"message": "\"STROMAUSGANG\" has not been declared as a property alias in relation \"000000000000008697\" of \"@_xxxpb\".",
		"facility": "GF::eai:eproduct",
		"level": "Debug",
		"timeStamp": "2019-02-05T20:52:05.058Z"
	}, {
		"message": "\"CHASSIS\" has not been declared as a property alias in relation \"000000000000008699\" of \"@_xxxpb\".",
		"facility": "GF::eai:eproduct",
		"level": "Debug",
		"timeStamp": "2019-02-05T20:52:05.058Z"
	}, {
		"message": "\"QUERSCHNITT\" has not been declared as a property alias in relation \"000000000000008699\" of \"@_xxxpb\".",
		"facility": "GF::eai:eproduct",
		"level": "Debug",
		"timeStamp": "2019-02-05T20:52:05.058Z"
	}, {
		"message": "\"QUERSCHNITT\" has not been declared as a property alias in relation \"000000000000006811\" of \"@_xxxpb\".",
		"facility": "GF::eai:eproduct",
		"level": "Debug",
		"timeStamp": "2019-02-05T20:52:05.058Z"
	}, {
		"message": "\"STROMAUSGANG\" has not been declared as a property alias in relation \"000000000000006811\" of \"@_xxxpb\".",
		"facility": "GF::eai:eproduct",
		"level": "Debug",
		"timeStamp": "2019-02-05T20:52:05.058Z"
	}, {
		"message": "\"CHASSIS\" has not been declared as a property alias in relation \"000000000000006811\" of \"@_xxxpb\".",
		"facility": "GF::eai:eproduct",
		"level": "Debug",
		"timeStamp": "2019-02-05T20:52:05.058Z"
	}, {
		"message": "\"QUERSCHNITT\" has not been declared as a property alias in relation \"000000000000006812\" of \"@_xxxpb\".",
		"facility": "GF::eai:eproduct",
		"level": "Debug",
		"timeStamp": "2019-02-05T20:52:05.058Z"
	}, {
		"message": "\"STROMAUSGANG\" has not been declared as a property alias in relation \"000000000000006812\" of \"@_xxxpb\".",
		"facility": "GF::eai:eproduct",
		"level": "Debug",
		"timeStamp": "2019-02-05T20:52:05.058Z"
	}, {
		"message": "\"CHASSIS\" has not been declared as a property alias in relation \"000000000000006812\" of \"@_xxxpb\".",
		"facility": "GF::eai:eproduct",
		"level": "Debug",
		"timeStamp": "2019-02-05T20:52:05.058Z"
	}, {
		"message": "\"QUERSCHNITT\" has not been declared as a property alias in relation \"000000000000006817\" of \"@_xxxpb\".",
		"facility": "GF::eai:eproduct",
		"level": "Debug",
		"timeStamp": "2019-02-05T20:52:05.058Z"
	}, {
		"message": "\"STROMAUSGANG\" has not been declared as a property alias in relation \"000000000000006817\" of \"@_xxxpb\".",
		"facility": "GF::eai:eproduct",
		"level": "Debug",
		"timeStamp": "2019-02-05T20:52:05.058Z"
	}, {
		"message": "\"CHASSIS\" has not been declared as a property alias in relation \"000000000000006817\" of \"@_xxxpb\".",
		"facility": "GF::eai:eproduct",
		"level": "Debug",
		"timeStamp": "2019-02-05T20:52:05.058Z"
	}, {
		"message": "\"QUERSCHNITT\" has not been declared as a property alias in relation \"000000000000006819\" of \"@_xxxpb\".",
		"facility": "GF::eai:eproduct",
		"level": "Debug",
		"timeStamp": "2019-02-05T20:52:05.058Z"
	}, {
		"message": "\"STROMAUSGANG\" has not been declared as a property alias in relation \"000000000000006819\" of \"@_xxxpb\".",
		"facility": "GF::eai:eproduct",
		"level": "Debug",
		"timeStamp": "2019-02-05T20:52:05.058Z"
	}, {
		"message": "\"CHASSIS\" has not been declared as a property alias in relation \"000000000000006819\" of \"@_xxxpb\".",
		"facility": "GF::eai:eproduct",
		"level": "Debug",
		"timeStamp": "2019-02-05T20:52:05.058Z"
	}, {
		"message": "\"QUERSCHNITT\" has not been declared as a property alias in relation \"000000000000006818\" of \"@_xxxpb\".",
		"facility": "GF::eai:eproduct",
		"level": "Debug",
		"timeStamp": "2019-02-05T20:52:05.058Z"
	}, {
		"message": "\"STROMAUSGANG\" has not been declared as a property alias in relation \"000000000000006818\" of \"@_xxxpb\".",
		"facility": "GF::eai:eproduct",
		"level": "Debug",
		"timeStamp": "2019-02-05T20:52:05.058Z"
	}, {
		"message": "\"CHASSIS\" has not been declared as a property alias in relation \"000000000000006818\" of \"@_xxxpb\".",
		"facility": "GF::eai:eproduct",
		"level": "Debug",
		"timeStamp": "2019-02-05T20:52:05.058Z"
	}, {
		"message": "\"QUERSCHNITT\" has not been declared as a property alias in relation \"000000000000008700\" of \"@_xxxpb\".",
		"facility": "GF::eai:eproduct",
		"level": "Debug",
		"timeStamp": "2019-02-05T20:52:05.058Z"
	}, {
		"message": "\"STROMAUSGANG\" has not been declared as a property alias in relation \"000000000000008700\" of \"@_xxxpb\".",
		"facility": "GF::eai:eproduct",
		"level": "Debug",
		"timeStamp": "2019-02-05T20:52:05.058Z"
	}, {
		"message": "\"CHASSIS\" has not been declared as a property alias in relation \"000000000000008700\" of \"@_xxxpb\".",
		"facility": "GF::eai:eproduct",
		"level": "Debug",
		"timeStamp": "2019-02-05T20:52:05.058Z"
	}, {
		"message": "\"QUERSCHNITT\" has not been declared as a property alias in relation \"000000000000008701\" of \"@_xxxpb\".",
		"facility": "GF::eai:eproduct",
		"level": "Debug",
		"timeStamp": "2019-02-05T20:52:05.058Z"
	}, {
		"message": "\"STROMAUSGANG\" has not been declared as a property alias in relation \"000000000000008701\" of \"@_xxxpb\".",
		"facility": "GF::eai:eproduct",
		"level": "Debug",
		"timeStamp": "2019-02-05T20:52:05.058Z"
	}, {
		"message": "\"CHASSIS\" has not been declared as a property alias in relation \"000000000000008701\" of \"@_xxxpb\".",
		"facility": "GF::eai:eproduct",
		"level": "Debug",
		"timeStamp": "2019-02-05T20:52:05.058Z"
	}, {
		"message": "\"QUERSCHNITT\" has not been declared as a property alias in relation \"000000000000008702\" of \"@_xxxpb\".",
		"facility": "GF::eai:eproduct",
		"level": "Debug",
		"timeStamp": "2019-02-05T20:52:05.058Z"
	}, {
		"message": "\"STROMAUSGANG\" has not been declared as a property alias in relation \"000000000000008702\" of \"@_xxxpb\".",
		"facility": "GF::eai:eproduct",
		"level": "Debug",
		"timeStamp": "2019-02-05T20:52:05.058Z"
	}, {
		"message": "\"CHASSIS\" has not been declared as a property alias in relation \"000000000000008702\" of \"@_xxxpb\".",
		"facility": "GF::eai:eproduct",
		"level": "Debug",
		"timeStamp": "2019-02-05T20:52:05.058Z"
	}, {
		"message": "\"CHASSIS\" has not been declared as a property alias in relation \"000000000000006361\" of \"@_xxxpb\".",
		"facility": "GF::eai:eproduct",
		"level": "Debug",
		"timeStamp": "2019-02-05T20:52:05.058Z"
	}, {
		"message": "\"STROMAUSGANG\" has not been declared as a property alias in relation \"000000000000006361\" of \"@_xxxpb\".",
		"facility": "GF::eai:eproduct",
		"level": "Debug",
		"timeStamp": "2019-02-05T20:52:05.058Z"
	}, {
		"message": "\"QUERSCHNITT\" has not been declared as a property alias in relation \"000000000000006361\" of \"@_xxxpb\".",
		"facility": "GF::eai:eproduct",
		"level": "Debug",
		"timeStamp": "2019-02-05T20:52:05.058Z"
	}, {
		"message": "\"EINHEIT1\" has not been declared as a property alias in relation \"000000000000006361\" of \"@_xxxpb\".",
		"facility": "GF::eai:eproduct",
		"level": "Debug",
		"timeStamp": "2019-02-05T20:52:05.059Z"
	}, {
		"message": "\"INT_EXT\" has not been declared as a property alias in relation \"000000000000006361\" of \"@_xxxpb\".",
		"facility": "GF::eai:eproduct",
		"level": "Debug",
		"timeStamp": "2019-02-05T20:52:05.059Z"
	}, {
		"message": "\"PB_VAR\" has not been declared as a property alias in relation \"000000000000006361\" of \"@_xxxpb\".",
		"facility": "GF::eai:eproduct",
		"level": "Debug",
		"timeStamp": "2019-02-05T20:52:05.059Z"
	}, {
		"message": "\"CHASSIS\" has not been declared as a property alias in relation \"000000000000006357\" of \"@_xxxpb\".",
		"facility": "GF::eai:eproduct",
		"level": "Debug",
		"timeStamp": "2019-02-05T20:52:05.059Z"
	}, {
		"message": "\"STROMAUSGANG\" has not been declared as a property alias in relation \"000000000000006357\" of \"@_xxxpb\".",
		"facility": "GF::eai:eproduct",
		"level": "Debug",
		"timeStamp": "2019-02-05T20:52:05.059Z"
	}, {
		"message": "\"PB_VAR\" has not been declared as a property alias in relation \"000000000000006357\" of \"@_xxxpb\".",
		"facility": "GF::eai:eproduct",
		"level": "Debug",
		"timeStamp": "2019-02-05T20:52:05.059Z"
	}, {
		"message": "\"QUERSCHNITT\" has not been declared as a property alias in relation \"000000000000006357\" of \"@_xxxpb\".",
		"facility": "GF::eai:eproduct",
		"level": "Debug",
		"timeStamp": "2019-02-05T20:52:05.059Z"
	}, {
		"message": "\"EINHEIT2\" has not been declared as a property alias in relation \"000000000000006357\" of \"@_xxxpb\".",
		"facility": "GF::eai:eproduct",
		"level": "Debug",
		"timeStamp": "2019-02-05T20:52:05.059Z"
	}, {
		"message": "\"INT_EXT\" has not been declared as a property alias in relation \"000000000000006357\" of \"@_xxxpb\".",
		"facility": "GF::eai:eproduct",
		"level": "Debug",
		"timeStamp": "2019-02-05T20:52:05.059Z"
	}, {
		"message": "\"CHASSIS\" has not been declared as a property alias in relation \"000000000000006360\" of \"@_xxxpb\".",
		"facility": "GF::eai:eproduct",
		"level": "Debug",
		"timeStamp": "2019-02-05T20:52:05.059Z"
	}, {
		"message": "\"STROMAUSGANG\" has not been declared as a property alias in relation \"000000000000006360\" of \"@_xxxpb\".",
		"facility": "GF::eai:eproduct",
		"level": "Debug",
		"timeStamp": "2019-02-05T20:52:05.059Z"
	}, {
		"message": "\"QUERSCHNITT\" has not been declared as a property alias in relation \"000000000000006360\" of \"@_xxxpb\".",
		"facility": "GF::eai:eproduct",
		"level": "Debug",
		"timeStamp": "2019-02-05T20:52:05.059Z"
	}, {
		"message": "\"EINHEIT3\" has not been declared as a property alias in relation \"000000000000006360\" of \"@_xxxpb\".",
		"facility": "GF::eai:eproduct",
		"level": "Debug",
		"timeStamp": "2019-02-05T20:52:05.059Z"
	}, {
		"message": "\"INT_EXT\" has not been declared as a property alias in relation \"000000000000006360\" of \"@_xxxpb\".",
		"facility": "GF::eai:eproduct",
		"level": "Debug",
		"timeStamp": "2019-02-05T20:52:05.059Z"
	}, {
		"message": "\"PB_VAR\" has not been declared as a property alias in relation \"000000000000006360\" of \"@_xxxpb\".",
		"facility": "GF::eai:eproduct",
		"level": "Debug",
		"timeStamp": "2019-02-05T20:52:05.059Z"
	}, {
		"message": "\"CHASSIS\" has not been declared as a property alias in relation \"000000000000006358\" of \"@_xxxpb\".",
		"facility": "GF::eai:eproduct",
		"level": "Debug",
		"timeStamp": "2019-02-05T20:52:05.059Z"
	}, {
		"message": "\"STROMAUSGANG\" has not been declared as a property alias in relation \"000000000000006358\" of \"@_xxxpb\".",
		"facility": "GF::eai:eproduct",
		"level": "Debug",
		"timeStamp": "2019-02-05T20:52:05.059Z"
	}, {
		"message": "\"QUERSCHNITT\" has not been declared as a property alias in relation \"000000000000006358\" of \"@_xxxpb\".",
		"facility": "GF::eai:eproduct",
		"level": "Debug",
		"timeStamp": "2019-02-05T20:52:05.059Z"
	}, {
		"message": "\"EINHEIT4\" has not been declared as a property alias in relation \"000000000000006358\" of \"@_xxxpb\".",
		"facility": "GF::eai:eproduct",
		"level": "Debug",
		"timeStamp": "2019-02-05T20:52:05.059Z"
	}, {
		"message": "\"INT_EXT\" has not been declared as a property alias in relation \"000000000000006358\" of \"@_xxxpb\".",
		"facility": "GF::eai:eproduct",
		"level": "Debug",
		"timeStamp": "2019-02-05T20:52:05.059Z"
	}, {
		"message": "\"CHASSIS\" has not been declared as a property alias in relation \"000000000000006359\" of \"@_xxxpb\".",
		"facility": "GF::eai:eproduct",
		"level": "Debug",
		"timeStamp": "2019-02-05T20:52:05.059Z"
	}, {
		"message": "\"STROMAUSGANG\" has not been declared as a property alias in relation \"000000000000006359\" of \"@_xxxpb\".",
		"facility": "GF::eai:eproduct",
		"level": "Debug",
		"timeStamp": "2019-02-05T20:52:05.059Z"
	}, {
		"message": "\"QUERSCHNITT\" has not been declared as a property alias in relation \"000000000000006359\" of \"@_xxxpb\".",
		"facility": "GF::eai:eproduct",
		"level": "Debug",
		"timeStamp": "2019-02-05T20:52:05.059Z"
	}, {
		"message": "\"EINHEIT5\" has not been declared as a property alias in relation \"000000000000006359\" of \"@_xxxpb\".",
		"facility": "GF::eai:eproduct",
		"level": "Debug",
		"timeStamp": "2019-02-05T20:52:05.059Z"
	}, {
		"message": "\"INT_EXT\" has not been declared as a property alias in relation \"000000000000006359\" of \"@_xxxpb\".",
		"facility": "GF::eai:eproduct",
		"level": "Debug",
		"timeStamp": "2019-02-05T20:52:05.059Z"
	}, {
		"message": "\"CHASSIS\" has not been declared as a property alias in relation \"000000000000008081\" of \"@_xxxpb\".",
		"facility": "GF::eai:eproduct",
		"level": "Debug",
		"timeStamp": "2019-02-05T20:52:05.059Z"
	}, {
		"message": "\"STROMAUSGANG\" has not been declared as a property alias in relation \"000000000000008081\" of \"@_xxxpb\".",
		"facility": "GF::eai:eproduct",
		"level": "Debug",
		"timeStamp": "2019-02-05T20:52:05.059Z"
	}, {
		"message": "\"QUERSCHNITT\" has not been declared as a property alias in relation \"000000000000008081\" of \"@_xxxpb\".",
		"facility": "GF::eai:eproduct",
		"level": "Debug",
		"timeStamp": "2019-02-05T20:52:05.059Z"
	}, {
		"message": "\"EINHEIT6\" has not been declared as a property alias in relation \"000000000000008081\" of \"@_xxxpb\".",
		"facility": "GF::eai:eproduct",
		"level": "Debug",
		"timeStamp": "2019-02-05T20:52:05.059Z"
	}, {
		"message": "\"INT_EXT\" has not been declared as a property alias in relation \"000000000000008081\" of \"@_xxxpb\".",
		"facility": "GF::eai:eproduct",
		"level": "Debug",
		"timeStamp": "2019-02-05T20:52:05.059Z"
	}, {
		"message": "\"CHASSIS\" has not been declared as a property alias in relation \"000000000000008082\" of \"@_xxxpb\".",
		"facility": "GF::eai:eproduct",
		"level": "Debug",
		"timeStamp": "2019-02-05T20:52:05.059Z"
	}, {
		"message": "\"STROMAUSGANG\" has not been declared as a property alias in relation \"000000000000008082\" of \"@_xxxpb\".",
		"facility": "GF::eai:eproduct",
		"level": "Debug",
		"timeStamp": "2019-02-05T20:52:05.059Z"
	}, {
		"message": "\"QUERSCHNITT\" has not been declared as a property alias in relation \"000000000000008082\" of \"@_xxxpb\".",
		"facility": "GF::eai:eproduct",
		"level": "Debug",
		"timeStamp": "2019-02-05T20:52:05.059Z"
	}, {
		"message": "\"EINHEIT7\" has not been declared as a property alias in relation \"000000000000008082\" of \"@_xxxpb\".",
		"facility": "GF::eai:eproduct",
		"level": "Debug",
		"timeStamp": "2019-02-05T20:52:05.059Z"
	}, {
		"message": "\"INT_EXT\" has not been declared as a property alias in relation \"000000000000008082\" of \"@_xxxpb\".",
		"facility": "GF::eai:eproduct",
		"level": "Debug",
		"timeStamp": "2019-02-05T20:52:05.059Z"
	}, {
		"message": "\"CHASSIS\" has not been declared as a property alias in relation \"000000000000008083\" of \"@_xxxpb\".",
		"facility": "GF::eai:eproduct",
		"level": "Debug",
		"timeStamp": "2019-02-05T20:52:05.059Z"
	}, {
		"message": "\"STROMAUSGANG\" has not been declared as a property alias in relation \"000000000000008083\" of \"@_xxxpb\".",
		"facility": "GF::eai:eproduct",
		"level": "Debug",
		"timeStamp": "2019-02-05T20:52:05.059Z"
	}, {
		"message": "\"QUERSCHNITT\" has not been declared as a property alias in relation \"000000000000008083\" of \"@_xxxpb\".",
		"facility": "GF::eai:eproduct",
		"level": "Debug",
		"timeStamp": "2019-02-05T20:52:05.059Z"
	}, {
		"message": "\"EINHEIT8\" has not been declared as a property alias in relation \"000000000000008083\" of \"@_xxxpb\".",
		"facility": "GF::eai:eproduct",
		"level": "Debug",
		"timeStamp": "2019-02-05T20:52:05.059Z"
	}, {
		"message": "\"INT_EXT\" has not been declared as a property alias in relation \"000000000000008083\" of \"@_xxxpb\".",
		"facility": "GF::eai:eproduct",
		"level": "Debug",
		"timeStamp": "2019-02-05T20:52:05.059Z"
	}, {
		"message": "\"CHASSIS\" has not been declared as a property alias in relation \"000000000000008084\" of \"@_xxxpb\".",
		"facility": "GF::eai:eproduct",
		"level": "Debug",
		"timeStamp": "2019-02-05T20:52:05.059Z"
	}, {
		"message": "\"STROMAUSGANG\" has not been declared as a property alias in relation \"000000000000008084\" of \"@_xxxpb\".",
		"facility": "GF::eai:eproduct",
		"level": "Debug",
		"timeStamp": "2019-02-05T20:52:05.059Z"
	}, {
		"message": "\"QUERSCHNITT\" has not been declared as a property alias in relation \"000000000000008084\" of \"@_xxxpb\".",
		"facility": "GF::eai:eproduct",
		"level": "Debug",
		"timeStamp": "2019-02-05T20:52:05.059Z"
	}, {
		"message": "\"EINHEIT9\" has not been declared as a property alias in relation \"000000000000008084\" of \"@_xxxpb\".",
		"facility": "GF::eai:eproduct",
		"level": "Debug",
		"timeStamp": "2019-02-05T20:52:05.059Z"
	}, {
		"message": "\"INT_EXT\" has not been declared as a property alias in relation \"000000000000008084\" of \"@_xxxpb\".",
		"facility": "GF::eai:eproduct",
		"level": "Debug",
		"timeStamp": "2019-02-05T20:52:05.059Z"
	}, {
		"message": "\"INT_EXT\" has not been declared as a property alias in relation \"000000000000014166\" of \"@_xxxpb\".",
		"facility": "GF::eai:eproduct",
		"level": "Debug",
		"timeStamp": "2019-02-05T20:52:05.059Z"
	}, {
		"message": "\"MODUL1\" has not been declared as a property alias in relation \"000000000000014166\" of \"@_xxxpb\".",
		"facility": "GF::eai:eproduct",
		"level": "Debug",
		"timeStamp": "2019-02-05T20:52:05.059Z"
	}, {
		"message": "\"PB_VAR\" has not been declared as a property alias in relation \"000000000000014166\" of \"@_xxxpb\".",
		"facility": "GF::eai:eproduct",
		"level": "Debug",
		"timeStamp": "2019-02-05T20:52:05.059Z"
	}, {
		"message": "\"INT_EXT\" has not been declared as a property alias in relation \"000000000000014167\" of \"@_xxxpb\".",
		"facility": "GF::eai:eproduct",
		"level": "Debug",
		"timeStamp": "2019-02-05T20:52:05.059Z"
	}, {
		"message": "\"MODUL1\" has not been declared as a property alias in relation \"000000000000014167\" of \"@_xxxpb\".",
		"facility": "GF::eai:eproduct",
		"level": "Debug",
		"timeStamp": "2019-02-05T20:52:05.059Z"
	}, {
		"message": "\"MODUL2\" has not been declared as a property alias in relation \"000000000000014167\" of \"@_xxxpb\".",
		"facility": "GF::eai:eproduct",
		"level": "Debug",
		"timeStamp": "2019-02-05T20:52:05.059Z"
	}, {
		"message": "\"MODUL1\" has not been declared as a property alias in relation \"000000000000014167\" of \"@_xxxpb\".",
		"facility": "GF::eai:eproduct",
		"level": "Debug",
		"timeStamp": "2019-02-05T20:52:05.059Z"
	}, {
		"message": "\"INT_EXT\" has not been declared as a property alias in relation \"000000000000014168\" of \"@_xxxpb\".",
		"facility": "GF::eai:eproduct",
		"level": "Debug",
		"timeStamp": "2019-02-05T20:52:05.059Z"
	}, {
		"message": "\"MODUL3\" has not been declared as a property alias in relation \"000000000000014168\" of \"@_xxxpb\".",
		"facility": "GF::eai:eproduct",
		"level": "Debug",
		"timeStamp": "2019-02-05T20:52:05.059Z"
	}, {
		"message": "\"MODUL1\" has not been declared as a property alias in relation \"000000000000014168\" of \"@_xxxpb\".",
		"facility": "GF::eai:eproduct",
		"level": "Debug",
		"timeStamp": "2019-02-05T20:52:05.059Z"
	}, {
		"message": "\"QUERSCHNITT\" has not been declared as a property alias in relation \"000000000000006747\" of \"@_xxxpb\".",
		"facility": "GF::eai:eproduct",
		"level": "Debug",
		"timeStamp": "2019-02-05T20:52:05.059Z"
	}, {
		"message": "\"QUERSCHNITT\" has not been declared as a property alias in relation \"000000000000006742\" of \"@_xxxpb\".",
		"facility": "GF::eai:eproduct",
		"level": "Debug",
		"timeStamp": "2019-02-05T20:52:05.059Z"
	}, {
		"message": "\"CHASSIS\" has not been declared as a property alias in relation \"000000000000006743\" of \"@_xxxpb\".",
		"facility": "GF::eai:eproduct",
		"level": "Debug",
		"timeStamp": "2019-02-05T20:52:05.059Z"
	}, {
		"message": "\"QUERSCHNITT\" has not been declared as a property alias in relation \"000000000000006743\" of \"@_xxxpb\".",
		"facility": "GF::eai:eproduct",
		"level": "Debug",
		"timeStamp": "2019-02-05T20:52:05.059Z"
	}, {
		"message": "\"CHASSIS\" has not been declared as a property alias in relation \"000000000000006745\" of \"@_xxxpb\".",
		"facility": "GF::eai:eproduct",
		"level": "Debug",
		"timeStamp": "2019-02-05T20:52:05.059Z"
	}, {
		"message": "\"QUERSCHNITT\" has not been declared as a property alias in relation \"000000000000006745\" of \"@_xxxpb\".",
		"facility": "GF::eai:eproduct",
		"level": "Debug",
		"timeStamp": "2019-02-05T20:52:05.059Z"
	}, {
		"message": "\"CHASSIS\" has not been declared as a property alias in relation \"000000000000006744\" of \"@_xxxpb\".",
		"facility": "GF::eai:eproduct",
		"level": "Debug",
		"timeStamp": "2019-02-05T20:52:05.059Z"
	}, {
		"message": "\"QUERSCHNITT\" has not been declared as a property alias in relation \"000000000000006744\" of \"@_xxxpb\".",
		"facility": "GF::eai:eproduct",
		"level": "Debug",
		"timeStamp": "2019-02-05T20:52:05.059Z"
	}, {
		"message": "\"CHASSIS\" has not been declared as a property alias in relation \"000000000000006746\" of \"@_xxxpb\".",
		"facility": "GF::eai:eproduct",
		"level": "Debug",
		"timeStamp": "2019-02-05T20:52:05.059Z"
	}, {
		"message": "\"QUERSCHNITT\" has not been declared as a property alias in relation \"000000000000006746\" of \"@_xxxpb\".",
		"facility": "GF::eai:eproduct",
		"level": "Debug",
		"timeStamp": "2019-02-05T20:52:05.059Z"
	}, {
		"message": "\"CHASSIS\" has not been declared as a property alias in relation \"000000000000008548\" of \"@_xxxpb\".",
		"facility": "GF::eai:eproduct",
		"level": "Debug",
		"timeStamp": "2019-02-05T20:52:05.059Z"
	}, {
		"message": "\"QUERSCHNITT\" has not been declared as a property alias in relation \"000000000000008548\" of \"@_xxxpb\".",
		"facility": "GF::eai:eproduct",
		"level": "Debug",
		"timeStamp": "2019-02-05T20:52:05.059Z"
	}, {
		"message": "\"CHASSIS\" has not been declared as a property alias in relation \"000000000000008551\" of \"@_xxxpb\".",
		"facility": "GF::eai:eproduct",
		"level": "Debug",
		"timeStamp": "2019-02-05T20:52:05.059Z"
	}, {
		"message": "\"QUERSCHNITT\" has not been declared as a property alias in relation \"000000000000008551\" of \"@_xxxpb\".",
		"facility": "GF::eai:eproduct",
		"level": "Debug",
		"timeStamp": "2019-02-05T20:52:05.059Z"
	}, {
		"message": "\"CHASSIS\" has not been declared as a property alias in relation \"000000000000008554\" of \"@_xxxpb\".",
		"facility": "GF::eai:eproduct",
		"level": "Debug",
		"timeStamp": "2019-02-05T20:52:05.059Z"
	}, {
		"message": "\"QUERSCHNITT\" has not been declared as a property alias in relation \"000000000000008554\" of \"@_xxxpb\".",
		"facility": "GF::eai:eproduct",
		"level": "Debug",
		"timeStamp": "2019-02-05T20:52:05.059Z"
	}, {
		"message": "\"CHASSIS\" has not been declared as a property alias in relation \"000000000000008670\" of \"@_xxxpb\".",
		"facility": "GF::eai:eproduct",
		"level": "Debug",
		"timeStamp": "2019-02-05T20:52:05.059Z"
	}, {
		"message": "\"QUERSCHNITT\" has not been declared as a property alias in relation \"000000000000008670\" of \"@_xxxpb\".",
		"facility": "GF::eai:eproduct",
		"level": "Debug",
		"timeStamp": "2019-02-05T20:52:05.059Z"
	}, {
		"message": "\"QUERSCHNITT\" has not been declared as a property alias in relation \"000000000000005080\" of \"@_xxxpb\".",
		"facility": "GF::eai:eproduct",
		"level": "Debug",
		"timeStamp": "2019-02-05T20:52:05.059Z"
	}, {
		"message": "\"EINHEIT1\" has not been declared as a property alias in relation \"000000000000005080\" of \"@_xxxpb\".",
		"facility": "GF::eai:eproduct",
		"level": "Debug",
		"timeStamp": "2019-02-05T20:52:05.059Z"
	}, {
		"message": "\"QUERSCHNITT\" has not been declared as a property alias in relation \"000000000000005081\" of \"@_xxxpb\".",
		"facility": "GF::eai:eproduct",
		"level": "Debug",
		"timeStamp": "2019-02-05T20:52:05.059Z"
	}, {
		"message": "\"QUERSCHNITT\" has not been declared as a property alias in relation \"000000000000005070\" of \"@_xxxpb\".",
		"facility": "GF::eai:eproduct",
		"level": "Debug",
		"timeStamp": "2019-02-05T20:52:05.059Z"
	}, {
		"message": "\"EINHEIT1\" has not been declared as a property alias in relation \"000000000000005070\" of \"@_xxxpb\".",
		"facility": "GF::eai:eproduct",
		"level": "Debug",
		"timeStamp": "2019-02-05T20:52:05.059Z"
	}, {
		"message": "\"QUERSCHNITT\" has not been declared as a property alias in relation \"000000000000005071\" of \"@_xxxpb\".",
		"facility": "GF::eai:eproduct",
		"level": "Debug",
		"timeStamp": "2019-02-05T20:52:05.059Z"
	}, {
		"message": "\"CHASSIS\" has not been declared as a property alias in relation \"000000000000005072\" of \"@_xxxpb\".",
		"facility": "GF::eai:eproduct",
		"level": "Debug",
		"timeStamp": "2019-02-05T20:52:05.059Z"
	}, {
		"message": "\"QUERSCHNITT\" has not been declared as a property alias in relation \"000000000000005072\" of \"@_xxxpb\".",
		"facility": "GF::eai:eproduct",
		"level": "Debug",
		"timeStamp": "2019-02-05T20:52:05.059Z"
	}, {
		"message": "\"EINHEIT1\" has not been declared as a property alias in relation \"000000000000005072\" of \"@_xxxpb\".",
		"facility": "GF::eai:eproduct",
		"level": "Debug",
		"timeStamp": "2019-02-05T20:52:05.059Z"
	}, {
		"message": "\"CHASSIS\" has not been declared as a property alias in relation \"000000000000005073\" of \"@_xxxpb\".",
		"facility": "GF::eai:eproduct",
		"level": "Debug",
		"timeStamp": "2019-02-05T20:52:05.059Z"
	}, {
		"message": "\"QUERSCHNITT\" has not been declared as a property alias in relation \"000000000000005073\" of \"@_xxxpb\".",
		"facility": "GF::eai:eproduct",
		"level": "Debug",
		"timeStamp": "2019-02-05T20:52:05.059Z"
	}, {
		"message": "\"CHASSIS\" has not been declared as a property alias in relation \"000000000000005074\" of \"@_xxxpb\".",
		"facility": "GF::eai:eproduct",
		"level": "Debug",
		"timeStamp": "2019-02-05T20:52:05.059Z"
	}, {
		"message": "\"QUERSCHNITT\" has not been declared as a property alias in relation \"000000000000005074\" of \"@_xxxpb\".",
		"facility": "GF::eai:eproduct",
		"level": "Debug",
		"timeStamp": "2019-02-05T20:52:05.059Z"
	}, {
		"message": "\"EINHEIT1\" has not been declared as a property alias in relation \"000000000000005074\" of \"@_xxxpb\".",
		"facility": "GF::eai:eproduct",
		"level": "Debug",
		"timeStamp": "2019-02-05T20:52:05.059Z"
	}, {
		"message": "\"CHASSIS\" has not been declared as a property alias in relation \"000000000000005075\" of \"@_xxxpb\".",
		"facility": "GF::eai:eproduct",
		"level": "Debug",
		"timeStamp": "2019-02-05T20:52:05.059Z"
	}, {
		"message": "\"QUERSCHNITT\" has not been declared as a property alias in relation \"000000000000005075\" of \"@_xxxpb\".",
		"facility": "GF::eai:eproduct",
		"level": "Debug",
		"timeStamp": "2019-02-05T20:52:05.060Z"
	}, {
		"message": "\"CHASSIS\" has not been declared as a property alias in relation \"000000000000005076\" of \"@_xxxpb\".",
		"facility": "GF::eai:eproduct",
		"level": "Debug",
		"timeStamp": "2019-02-05T20:52:05.060Z"
	}, {
		"message": "\"QUERSCHNITT\" has not been declared as a property alias in relation \"000000000000005076\" of \"@_xxxpb\".",
		"facility": "GF::eai:eproduct",
		"level": "Debug",
		"timeStamp": "2019-02-05T20:52:05.060Z"
	}, {
		"message": "\"EINHEIT1\" has not been declared as a property alias in relation \"000000000000005076\" of \"@_xxxpb\".",
		"facility": "GF::eai:eproduct",
		"level": "Debug",
		"timeStamp": "2019-02-05T20:52:05.060Z"
	}, {
		"message": "\"CHASSIS\" has not been declared as a property alias in relation \"000000000000005077\" of \"@_xxxpb\".",
		"facility": "GF::eai:eproduct",
		"level": "Debug",
		"timeStamp": "2019-02-05T20:52:05.060Z"
	}, {
		"message": "\"QUERSCHNITT\" has not been declared as a property alias in relation \"000000000000005077\" of \"@_xxxpb\".",
		"facility": "GF::eai:eproduct",
		"level": "Debug",
		"timeStamp": "2019-02-05T20:52:05.060Z"
	}, {
		"message": "\"CHASSIS\" has not been declared as a property alias in relation \"000000000000005078\" of \"@_xxxpb\".",
		"facility": "GF::eai:eproduct",
		"level": "Debug",
		"timeStamp": "2019-02-05T20:52:05.060Z"
	}, {
		"message": "\"QUERSCHNITT\" has not been declared as a property alias in relation \"000000000000005078\" of \"@_xxxpb\".",
		"facility": "GF::eai:eproduct",
		"level": "Debug",
		"timeStamp": "2019-02-05T20:52:05.060Z"
	}, {
		"message": "\"EINHEIT1\" has not been declared as a property alias in relation \"000000000000005078\" of \"@_xxxpb\".",
		"facility": "GF::eai:eproduct",
		"level": "Debug",
		"timeStamp": "2019-02-05T20:52:05.060Z"
	}, {
		"message": "\"CHASSIS\" has not been declared as a property alias in relation \"000000000000005079\" of \"@_xxxpb\".",
		"facility": "GF::eai:eproduct",
		"level": "Debug",
		"timeStamp": "2019-02-05T20:52:05.060Z"
	}, {
		"message": "\"QUERSCHNITT\" has not been declared as a property alias in relation \"000000000000005079\" of \"@_xxxpb\".",
		"facility": "GF::eai:eproduct",
		"level": "Debug",
		"timeStamp": "2019-02-05T20:52:05.060Z"
	}, {
		"message": "\"CHASSIS\" has not been declared as a property alias in relation \"000000000000008549\" of \"@_xxxpb\".",
		"facility": "GF::eai:eproduct",
		"level": "Debug",
		"timeStamp": "2019-02-05T20:52:05.060Z"
	}, {
		"message": "\"QUERSCHNITT\" has not been declared as a property alias in relation \"000000000000008549\" of \"@_xxxpb\".",
		"facility": "GF::eai:eproduct",
		"level": "Debug",
		"timeStamp": "2019-02-05T20:52:05.060Z"
	}, {
		"message": "\"EINHEIT1\" has not been declared as a property alias in relation \"000000000000008549\" of \"@_xxxpb\".",
		"facility": "GF::eai:eproduct",
		"level": "Debug",
		"timeStamp": "2019-02-05T20:52:05.060Z"
	}, {
		"message": "\"CHASSIS\" has not been declared as a property alias in relation \"000000000000008547\" of \"@_xxxpb\".",
		"facility": "GF::eai:eproduct",
		"level": "Debug",
		"timeStamp": "2019-02-05T20:52:05.060Z"
	}, {
		"message": "\"QUERSCHNITT\" has not been declared as a property alias in relation \"000000000000008547\" of \"@_xxxpb\".",
		"facility": "GF::eai:eproduct",
		"level": "Debug",
		"timeStamp": "2019-02-05T20:52:05.060Z"
	}, {
		"message": "\"CHASSIS\" has not been declared as a property alias in relation \"000000000000008552\" of \"@_xxxpb\".",
		"facility": "GF::eai:eproduct",
		"level": "Debug",
		"timeStamp": "2019-02-05T20:52:05.060Z"
	}, {
		"message": "\"QUERSCHNITT\" has not been declared as a property alias in relation \"000000000000008552\" of \"@_xxxpb\".",
		"facility": "GF::eai:eproduct",
		"level": "Debug",
		"timeStamp": "2019-02-05T20:52:05.060Z"
	}, {
		"message": "\"EINHEIT1\" has not been declared as a property alias in relation \"000000000000008552\" of \"@_xxxpb\".",
		"facility": "GF::eai:eproduct",
		"level": "Debug",
		"timeStamp": "2019-02-05T20:52:05.060Z"
	}, {
		"message": "\"CHASSIS\" has not been declared as a property alias in relation \"000000000000008550\" of \"@_xxxpb\".",
		"facility": "GF::eai:eproduct",
		"level": "Debug",
		"timeStamp": "2019-02-05T20:52:05.060Z"
	}, {
		"message": "\"QUERSCHNITT\" has not been declared as a property alias in relation \"000000000000008550\" of \"@_xxxpb\".",
		"facility": "GF::eai:eproduct",
		"level": "Debug",
		"timeStamp": "2019-02-05T20:52:05.060Z"
	}, {
		"message": "\"CHASSIS\" has not been declared as a property alias in relation \"000000000000008555\" of \"@_xxxpb\".",
		"facility": "GF::eai:eproduct",
		"level": "Debug",
		"timeStamp": "2019-02-05T20:52:05.060Z"
	}, {
		"message": "\"QUERSCHNITT\" has not been declared as a property alias in relation \"000000000000008555\" of \"@_xxxpb\".",
		"facility": "GF::eai:eproduct",
		"level": "Debug",
		"timeStamp": "2019-02-05T20:52:05.060Z"
	}, {
		"message": "\"EINHEIT1\" has not been declared as a property alias in relation \"000000000000008555\" of \"@_xxxpb\".",
		"facility": "GF::eai:eproduct",
		"level": "Debug",
		"timeStamp": "2019-02-05T20:52:05.060Z"
	}, {
		"message": "\"CHASSIS\" has not been declared as a property alias in relation \"000000000000008553\" of \"@_xxxpb\".",
		"facility": "GF::eai:eproduct",
		"level": "Debug",
		"timeStamp": "2019-02-05T20:52:05.060Z"
	}, {
		"message": "\"QUERSCHNITT\" has not been declared as a property alias in relation \"000000000000008553\" of \"@_xxxpb\".",
		"facility": "GF::eai:eproduct",
		"level": "Debug",
		"timeStamp": "2019-02-05T20:52:05.060Z"
	}, {
		"message": "\"CHASSIS\" has not been declared as a property alias in relation \"000000000000008671\" of \"@_xxxpb\".",
		"facility": "GF::eai:eproduct",
		"level": "Debug",
		"timeStamp": "2019-02-05T20:52:05.060Z"
	}, {
		"message": "\"QUERSCHNITT\" has not been declared as a property alias in relation \"000000000000008671\" of \"@_xxxpb\".",
		"facility": "GF::eai:eproduct",
		"level": "Debug",
		"timeStamp": "2019-02-05T20:52:05.060Z"
	}, {
		"message": "\"EINHEIT1\" has not been declared as a property alias in relation \"000000000000008671\" of \"@_xxxpb\".",
		"facility": "GF::eai:eproduct",
		"level": "Debug",
		"timeStamp": "2019-02-05T20:52:05.060Z"
	}, {
		"message": "\"CHASSIS\" has not been declared as a property alias in relation \"000000000000008669\" of \"@_xxxpb\".",
		"facility": "GF::eai:eproduct",
		"level": "Debug",
		"timeStamp": "2019-02-05T20:52:05.060Z"
	}, {
		"message": "\"QUERSCHNITT\" has not been declared as a property alias in relation \"000000000000008669\" of \"@_xxxpb\".",
		"facility": "GF::eai:eproduct",
		"level": "Debug",
		"timeStamp": "2019-02-05T20:52:05.060Z"
	}, {
		"message": "\"EINHEIT1\" has not been declared as a property alias in relation \"000000000000005069\" of \"@_xxxpb\".",
		"facility": "GF::eai:eproduct",
		"level": "Debug",
		"timeStamp": "2019-02-05T20:52:05.060Z"
	}, {
		"message": "\"EINHEIT2\" has not been declared as a property alias in relation \"000000000000005069\" of \"@_xxxpb\".",
		"facility": "GF::eai:eproduct",
		"level": "Debug",
		"timeStamp": "2019-02-05T20:52:05.060Z"
	}, {
		"message": "\"CHASSIS\" has not been declared as a property alias in relation \"000000000000005069\" of \"@_xxxpb\".",
		"facility": "GF::eai:eproduct",
		"level": "Debug",
		"timeStamp": "2019-02-05T20:52:05.060Z"
	}, {
		"message": "\"INT_EXT\" has not been declared as a property alias in relation \"000000000000005069\" of \"@_xxxpb\".",
		"facility": "GF::eai:eproduct",
		"level": "Debug",
		"timeStamp": "2019-02-05T20:52:05.060Z"
	}, {
		"message": "\"EINHEIT2\" has not been declared as a property alias in relation \"000000000000005065\" of \"@_xxxpb\".",
		"facility": "GF::eai:eproduct",
		"level": "Debug",
		"timeStamp": "2019-02-05T20:52:05.060Z"
	}, {
		"message": "\"EINHEIT3\" has not been declared as a property alias in relation \"000000000000005065\" of \"@_xxxpb\".",
		"facility": "GF::eai:eproduct",
		"level": "Debug",
		"timeStamp": "2019-02-05T20:52:05.060Z"
	}, {
		"message": "\"CHASSIS\" has not been declared as a property alias in relation \"000000000000005065\" of \"@_xxxpb\".",
		"facility": "GF::eai:eproduct",
		"level": "Debug",
		"timeStamp": "2019-02-05T20:52:05.060Z"
	}, {
		"message": "\"INT_EXT\" has not been declared as a property alias in relation \"000000000000005065\" of \"@_xxxpb\".",
		"facility": "GF::eai:eproduct",
		"level": "Debug",
		"timeStamp": "2019-02-05T20:52:05.060Z"
	}, {
		"message": "\"EINHEIT3\" has not been declared as a property alias in relation \"000000000000005066\" of \"@_xxxpb\".",
		"facility": "GF::eai:eproduct",
		"level": "Debug",
		"timeStamp": "2019-02-05T20:52:05.060Z"
	}, {
		"message": "\"EINHEIT4\" has not been declared as a property alias in relation \"000000000000005066\" of \"@_xxxpb\".",
		"facility": "GF::eai:eproduct",
		"level": "Debug",
		"timeStamp": "2019-02-05T20:52:05.060Z"
	}, {
		"message": "\"CHASSIS\" has not been declared as a property alias in relation \"000000000000005066\" of \"@_xxxpb\".",
		"facility": "GF::eai:eproduct",
		"level": "Debug",
		"timeStamp": "2019-02-05T20:52:05.060Z"
	}, {
		"message": "\"INT_EXT\" has not been declared as a property alias in relation \"000000000000005066\" of \"@_xxxpb\".",
		"facility": "GF::eai:eproduct",
		"level": "Debug",
		"timeStamp": "2019-02-05T20:52:05.060Z"
	}, {
		"message": "\"EINHEIT4\" has not been declared as a property alias in relation \"000000000000005067\" of \"@_xxxpb\".",
		"facility": "GF::eai:eproduct",
		"level": "Debug",
		"timeStamp": "2019-02-05T20:52:05.060Z"
	}, {
		"message": "\"EINHEIT5\" has not been declared as a property alias in relation \"000000000000005067\" of \"@_xxxpb\".",
		"facility": "GF::eai:eproduct",
		"level": "Debug",
		"timeStamp": "2019-02-05T20:52:05.060Z"
	}, {
		"message": "\"CHASSIS\" has not been declared as a property alias in relation \"000000000000005067\" of \"@_xxxpb\".",
		"facility": "GF::eai:eproduct",
		"level": "Debug",
		"timeStamp": "2019-02-05T20:52:05.060Z"
	}, {
		"message": "\"INT_EXT\" has not been declared as a property alias in relation \"000000000000005067\" of \"@_xxxpb\".",
		"facility": "GF::eai:eproduct",
		"level": "Debug",
		"timeStamp": "2019-02-05T20:52:05.060Z"
	}, {
		"message": "\"EINHEIT5\" has not been declared as a property alias in relation \"000000000000006784\" of \"@_xxxpb\".",
		"facility": "GF::eai:eproduct",
		"level": "Debug",
		"timeStamp": "2019-02-05T20:52:05.060Z"
	}, {
		"message": "\"EINHEIT6\" has not been declared as a property alias in relation \"000000000000006784\" of \"@_xxxpb\".",
		"facility": "GF::eai:eproduct",
		"level": "Debug",
		"timeStamp": "2019-02-05T20:52:05.060Z"
	}, {
		"message": "\"CHASSIS\" has not been declared as a property alias in relation \"000000000000006784\" of \"@_xxxpb\".",
		"facility": "GF::eai:eproduct",
		"level": "Debug",
		"timeStamp": "2019-02-05T20:52:05.060Z"
	}, {
		"message": "\"INT_EXT\" has not been declared as a property alias in relation \"000000000000006784\" of \"@_xxxpb\".",
		"facility": "GF::eai:eproduct",
		"level": "Debug",
		"timeStamp": "2019-02-05T20:52:05.060Z"
	}, {
		"message": "\"EINHEIT6\" has not been declared as a property alias in relation \"000000000000008662\" of \"@_xxxpb\".",
		"facility": "GF::eai:eproduct",
		"level": "Debug",
		"timeStamp": "2019-02-05T20:52:05.060Z"
	}, {
		"message": "\"EINHEIT7\" has not been declared as a property alias in relation \"000000000000008662\" of \"@_xxxpb\".",
		"facility": "GF::eai:eproduct",
		"level": "Debug",
		"timeStamp": "2019-02-05T20:52:05.060Z"
	}, {
		"message": "\"CHASSIS\" has not been declared as a property alias in relation \"000000000000008662\" of \"@_xxxpb\".",
		"facility": "GF::eai:eproduct",
		"level": "Debug",
		"timeStamp": "2019-02-05T20:52:05.060Z"
	}, {
		"message": "\"INT_EXT\" has not been declared as a property alias in relation \"000000000000008662\" of \"@_xxxpb\".",
		"facility": "GF::eai:eproduct",
		"level": "Debug",
		"timeStamp": "2019-02-05T20:52:05.060Z"
	}, {
		"message": "\"EINHEIT7\" has not been declared as a property alias in relation \"000000000000008664\" of \"@_xxxpb\".",
		"facility": "GF::eai:eproduct",
		"level": "Debug",
		"timeStamp": "2019-02-05T20:52:05.060Z"
	}, {
		"message": "\"EINHEIT8\" has not been declared as a property alias in relation \"000000000000008664\" of \"@_xxxpb\".",
		"facility": "GF::eai:eproduct",
		"level": "Debug",
		"timeStamp": "2019-02-05T20:52:05.060Z"
	}, {
		"message": "\"CHASSIS\" has not been declared as a property alias in relation \"000000000000008664\" of \"@_xxxpb\".",
		"facility": "GF::eai:eproduct",
		"level": "Debug",
		"timeStamp": "2019-02-05T20:52:05.060Z"
	}, {
		"message": "\"INT_EXT\" has not been declared as a property alias in relation \"000000000000008664\" of \"@_xxxpb\".",
		"facility": "GF::eai:eproduct",
		"level": "Debug",
		"timeStamp": "2019-02-05T20:52:05.060Z"
	}, {
		"message": "\"EINHEIT8\" has not been declared as a property alias in relation \"000000000000008663\" of \"@_xxxpb\".",
		"facility": "GF::eai:eproduct",
		"level": "Debug",
		"timeStamp": "2019-02-05T20:52:05.060Z"
	}, {
		"message": "\"EINHEIT9\" has not been declared as a property alias in relation \"000000000000008663\" of \"@_xxxpb\".",
		"facility": "GF::eai:eproduct",
		"level": "Debug",
		"timeStamp": "2019-02-05T20:52:05.060Z"
	}, {
		"message": "\"CHASSIS\" has not been declared as a property alias in relation \"000000000000008663\" of \"@_xxxpb\".",
		"facility": "GF::eai:eproduct",
		"level": "Debug",
		"timeStamp": "2019-02-05T20:52:05.060Z"
	}, {
		"message": "\"INT_EXT\" has not been declared as a property alias in relation \"000000000000008663\" of \"@_xxxpb\".",
		"facility": "GF::eai:eproduct",
		"level": "Debug",
		"timeStamp": "2019-02-05T20:52:05.060Z"
	}, {
		"message": "\"EINHEIT1\" has not been declared as a property alias in relation \"000000000000010143\" of \"@_xxxpb\".",
		"facility": "GF::eai:eproduct",
		"level": "Debug",
		"timeStamp": "2019-02-05T20:52:05.060Z"
	}, {
		"message": "\"EINHEIT2\" has not been declared as a property alias in relation \"000000000000010143\" of \"@_xxxpb\".",
		"facility": "GF::eai:eproduct",
		"level": "Debug",
		"timeStamp": "2019-02-05T20:52:05.060Z"
	}, {
		"message": "\"CHASSIS\" has not been declared as a property alias in relation \"000000000000010143\" of \"@_xxxpb\".",
		"facility": "GF::eai:eproduct",
		"level": "Debug",
		"timeStamp": "2019-02-05T20:52:05.060Z"
	}, {
		"message": "\"INT_EXT\" has not been declared as a property alias in relation \"000000000000010143\" of \"@_xxxpb\".",
		"facility": "GF::eai:eproduct",
		"level": "Debug",
		"timeStamp": "2019-02-05T20:52:05.060Z"
	}, {
		"message": "\"EINHEIT2\" has not been declared as a property alias in relation \"000000000000010150\" of \"@_xxxpb\".",
		"facility": "GF::eai:eproduct",
		"level": "Debug",
		"timeStamp": "2019-02-05T20:52:05.060Z"
	}, {
		"message": "\"EINHEIT3\" has not been declared as a property alias in relation \"000000000000010150\" of \"@_xxxpb\".",
		"facility": "GF::eai:eproduct",
		"level": "Debug",
		"timeStamp": "2019-02-05T20:52:05.060Z"
	}, {
		"message": "\"CHASSIS\" has not been declared as a property alias in relation \"000000000000010150\" of \"@_xxxpb\".",
		"facility": "GF::eai:eproduct",
		"level": "Debug",
		"timeStamp": "2019-02-05T20:52:05.060Z"
	}, {
		"message": "\"INT_EXT\" has not been declared as a property alias in relation \"000000000000010150\" of \"@_xxxpb\".",
		"facility": "GF::eai:eproduct",
		"level": "Debug",
		"timeStamp": "2019-02-05T20:52:05.060Z"
	}, {
		"message": "\"EINHEIT3\" has not been declared as a property alias in relation \"000000000000010145\" of \"@_xxxpb\".",
		"facility": "GF::eai:eproduct",
		"level": "Debug",
		"timeStamp": "2019-02-05T20:52:05.060Z"
	}, {
		"message": "\"EINHEIT4\" has not been declared as a property alias in relation \"000000000000010145\" of \"@_xxxpb\".",
		"facility": "GF::eai:eproduct",
		"level": "Debug",
		"timeStamp": "2019-02-05T20:52:05.060Z"
	}, {
		"message": "\"CHASSIS\" has not been declared as a property alias in relation \"000000000000010145\" of \"@_xxxpb\".",
		"facility": "GF::eai:eproduct",
		"level": "Debug",
		"timeStamp": "2019-02-05T20:52:05.060Z"
	}, {
		"message": "\"INT_EXT\" has not been declared as a property alias in relation \"000000000000010145\" of \"@_xxxpb\".",
		"facility": "GF::eai:eproduct",
		"level": "Debug",
		"timeStamp": "2019-02-05T20:52:05.060Z"
	}, {
		"message": "\"EINHEIT4\" has not been declared as a property alias in relation \"000000000000010146\" of \"@_xxxpb\".",
		"facility": "GF::eai:eproduct",
		"level": "Debug",
		"timeStamp": "2019-02-05T20:52:05.060Z"
	}, {
		"message": "\"EINHEIT5\" has not been declared as a property alias in relation \"000000000000010146\" of \"@_xxxpb\".",
		"facility": "GF::eai:eproduct",
		"level": "Debug",
		"timeStamp": "2019-02-05T20:52:05.060Z"
	}, {
		"message": "\"CHASSIS\" has not been declared as a property alias in relation \"000000000000010146\" of \"@_xxxpb\".",
		"facility": "GF::eai:eproduct",
		"level": "Debug",
		"timeStamp": "2019-02-05T20:52:05.060Z"
	}, {
		"message": "\"INT_EXT\" has not been declared as a property alias in relation \"000000000000010146\" of \"@_xxxpb\".",
		"facility": "GF::eai:eproduct",
		"level": "Debug",
		"timeStamp": "2019-02-05T20:52:05.060Z"
	}, {
		"message": "\"EINHEIT5\" has not been declared as a property alias in relation \"000000000000010153\" of \"@_xxxpb\".",
		"facility": "GF::eai:eproduct",
		"level": "Debug",
		"timeStamp": "2019-02-05T20:52:05.060Z"
	}, {
		"message": "\"EINHEIT6\" has not been declared as a property alias in relation \"000000000000010153\" of \"@_xxxpb\".",
		"facility": "GF::eai:eproduct",
		"level": "Debug",
		"timeStamp": "2019-02-05T20:52:05.060Z"
	}, {
		"message": "\"CHASSIS\" has not been declared as a property alias in relation \"000000000000010153\" of \"@_xxxpb\".",
		"facility": "GF::eai:eproduct",
		"level": "Debug",
		"timeStamp": "2019-02-05T20:52:05.060Z"
	}, {
		"message": "\"INT_EXT\" has not been declared as a property alias in relation \"000000000000010153\" of \"@_xxxpb\".",
		"facility": "GF::eai:eproduct",
		"level": "Debug",
		"timeStamp": "2019-02-05T20:52:05.060Z"
	}, {
		"message": "\"EINHEIT6\" has not been declared as a property alias in relation \"000000000000010144\" of \"@_xxxpb\".",
		"facility": "GF::eai:eproduct",
		"level": "Debug",
		"timeStamp": "2019-02-05T20:52:05.060Z"
	}, {
		"message": "\"EINHEIT7\" has not been declared as a property alias in relation \"000000000000010144\" of \"@_xxxpb\".",
		"facility": "GF::eai:eproduct",
		"level": "Debug",
		"timeStamp": "2019-02-05T20:52:05.060Z"
	}, {
		"message": "\"CHASSIS\" has not been declared as a property alias in relation \"000000000000010144\" of \"@_xxxpb\".",
		"facility": "GF::eai:eproduct",
		"level": "Debug",
		"timeStamp": "2019-02-05T20:52:05.060Z"
	}, {
		"message": "\"INT_EXT\" has not been declared as a property alias in relation \"000000000000010144\" of \"@_xxxpb\".",
		"facility": "GF::eai:eproduct",
		"level": "Debug",
		"timeStamp": "2019-02-05T20:52:05.060Z"
	}, {
		"message": "\"EINHEIT7\" has not been declared as a property alias in relation \"000000000000010155\" of \"@_xxxpb\".",
		"facility": "GF::eai:eproduct",
		"level": "Debug",
		"timeStamp": "2019-02-05T20:52:05.060Z"
	}, {
		"message": "\"EINHEIT8\" has not been declared as a property alias in relation \"000000000000010155\" of \"@_xxxpb\".",
		"facility": "GF::eai:eproduct",
		"level": "Debug",
		"timeStamp": "2019-02-05T20:52:05.060Z"
	}, {
		"message": "\"CHASSIS\" has not been declared as a property alias in relation \"000000000000010155\" of \"@_xxxpb\".",
		"facility": "GF::eai:eproduct",
		"level": "Debug",
		"timeStamp": "2019-02-05T20:52:05.060Z"
	}, {
		"message": "\"INT_EXT\" has not been declared as a property alias in relation \"000000000000010155\" of \"@_xxxpb\".",
		"facility": "GF::eai:eproduct",
		"level": "Debug",
		"timeStamp": "2019-02-05T20:52:05.060Z"
	}, {
		"message": "\"EINHEIT8\" has not been declared as a property alias in relation \"000000000000010154\" of \"@_xxxpb\".",
		"facility": "GF::eai:eproduct",
		"level": "Debug",
		"timeStamp": "2019-02-05T20:52:05.060Z"
	}, {
		"message": "\"EINHEIT9\" has not been declared as a property alias in relation \"000000000000010154\" of \"@_xxxpb\".",
		"facility": "GF::eai:eproduct",
		"level": "Debug",
		"timeStamp": "2019-02-05T20:52:05.060Z"
	}, {
		"message": "\"CHASSIS\" has not been declared as a property alias in relation \"000000000000010154\" of \"@_xxxpb\".",
		"facility": "GF::eai:eproduct",
		"level": "Debug",
		"timeStamp": "2019-02-05T20:52:05.060Z"
	}, {
		"message": "\"INT_EXT\" has not been declared as a property alias in relation \"000000000000010154\" of \"@_xxxpb\".",
		"facility": "GF::eai:eproduct",
		"level": "Debug",
		"timeStamp": "2019-02-05T20:52:05.060Z"
	}, {
		"message": "\"EINHEIT1\" has not been declared as a property alias in relation \"000000000000006016\" of \"@_xxxpb\".",
		"facility": "GF::eai:eproduct",
		"level": "Debug",
		"timeStamp": "2019-02-05T20:52:05.060Z"
	}, {
		"message": "\"EINHEIT2\" has not been declared as a property alias in relation \"000000000000006016\" of \"@_xxxpb\".",
		"facility": "GF::eai:eproduct",
		"level": "Debug",
		"timeStamp": "2019-02-05T20:52:05.060Z"
	}, {
		"message": "\"CHASSIS\" has not been declared as a property alias in relation \"000000000000006016\" of \"@_xxxpb\".",
		"facility": "GF::eai:eproduct",
		"level": "Debug",
		"timeStamp": "2019-02-05T20:52:05.060Z"
	}, {
		"message": "\"INT_EXT\" has not been declared as a property alias in relation \"000000000000006016\" of \"@_xxxpb\".",
		"facility": "GF::eai:eproduct",
		"level": "Debug",
		"timeStamp": "2019-02-05T20:52:05.060Z"
	}, {
		"message": "\"EINHEIT2\" has not been declared as a property alias in relation \"000000000000006012\" of \"@_xxxpb\".",
		"facility": "GF::eai:eproduct",
		"level": "Debug",
		"timeStamp": "2019-02-05T20:52:05.060Z"
	}, {
		"message": "\"EINHEIT3\" has not been declared as a property alias in relation \"000000000000006012\" of \"@_xxxpb\".",
		"facility": "GF::eai:eproduct",
		"level": "Debug",
		"timeStamp": "2019-02-05T20:52:05.060Z"
	}, {
		"message": "\"CHASSIS\" has not been declared as a property alias in relation \"000000000000006012\" of \"@_xxxpb\".",
		"facility": "GF::eai:eproduct",
		"level": "Debug",
		"timeStamp": "2019-02-05T20:52:05.060Z"
	}, {
		"message": "\"INT_EXT\" has not been declared as a property alias in relation \"000000000000006012\" of \"@_xxxpb\".",
		"facility": "GF::eai:eproduct",
		"level": "Debug",
		"timeStamp": "2019-02-05T20:52:05.060Z"
	}, {
		"message": "\"EINHEIT3\" has not been declared as a property alias in relation \"000000000000006013\" of \"@_xxxpb\".",
		"facility": "GF::eai:eproduct",
		"level": "Debug",
		"timeStamp": "2019-02-05T20:52:05.060Z"
	}, {
		"message": "\"EINHEIT4\" has not been declared as a property alias in relation \"000000000000006013\" of \"@_xxxpb\".",
		"facility": "GF::eai:eproduct",
		"level": "Debug",
		"timeStamp": "2019-02-05T20:52:05.060Z"
	}, {
		"message": "\"CHASSIS\" has not been declared as a property alias in relation \"000000000000006013\" of \"@_xxxpb\".",
		"facility": "GF::eai:eproduct",
		"level": "Debug",
		"timeStamp": "2019-02-05T20:52:05.060Z"
	}, {
		"message": "\"INT_EXT\" has not been declared as a property alias in relation \"000000000000006013\" of \"@_xxxpb\".",
		"facility": "GF::eai:eproduct",
		"level": "Debug",
		"timeStamp": "2019-02-05T20:52:05.060Z"
	}, {
		"message": "\"EINHEIT4\" has not been declared as a property alias in relation \"000000000000006014\" of \"@_xxxpb\".",
		"facility": "GF::eai:eproduct",
		"level": "Debug",
		"timeStamp": "2019-02-05T20:52:05.060Z"
	}, {
		"message": "\"EINHEIT5\" has not been declared as a property alias in relation \"000000000000006014\" of \"@_xxxpb\".",
		"facility": "GF::eai:eproduct",
		"level": "Debug",
		"timeStamp": "2019-02-05T20:52:05.060Z"
	}, {
		"message": "\"CHASSIS\" has not been declared as a property alias in relation \"000000000000006014\" of \"@_xxxpb\".",
		"facility": "GF::eai:eproduct",
		"level": "Debug",
		"timeStamp": "2019-02-05T20:52:05.060Z"
	}, {
		"message": "\"INT_EXT\" has not been declared as a property alias in relation \"000000000000006014\" of \"@_xxxpb\".",
		"facility": "GF::eai:eproduct",
		"level": "Debug",
		"timeStamp": "2019-02-05T20:52:05.060Z"
	}, {
		"message": "\"EINHEIT5\" has not been declared as a property alias in relation \"000000000000006015\" of \"@_xxxpb\".",
		"facility": "GF::eai:eproduct",
		"level": "Debug",
		"timeStamp": "2019-02-05T20:52:05.060Z"
	}, {
		"message": "\"EINHEIT6\" has not been declared as a property alias in relation \"000000000000006015\" of \"@_xxxpb\".",
		"facility": "GF::eai:eproduct",
		"level": "Debug",
		"timeStamp": "2019-02-05T20:52:05.060Z"
	}, {
		"message": "\"CHASSIS\" has not been declared as a property alias in relation \"000000000000006015\" of \"@_xxxpb\".",
		"facility": "GF::eai:eproduct",
		"level": "Debug",
		"timeStamp": "2019-02-05T20:52:05.060Z"
	}, {
		"message": "\"INT_EXT\" has not been declared as a property alias in relation \"000000000000006015\" of \"@_xxxpb\".",
		"facility": "GF::eai:eproduct",
		"level": "Debug",
		"timeStamp": "2019-02-05T20:52:05.060Z"
	}, {
		"message": "\"EINHEIT6\" has not been declared as a property alias in relation \"000000000000008665\" of \"@_xxxpb\".",
		"facility": "GF::eai:eproduct",
		"level": "Debug",
		"timeStamp": "2019-02-05T20:52:05.060Z"
	}, {
		"message": "\"EINHEIT7\" has not been declared as a property alias in relation \"000000000000008665\" of \"@_xxxpb\".",
		"facility": "GF::eai:eproduct",
		"level": "Debug",
		"timeStamp": "2019-02-05T20:52:05.060Z"
	}, {
		"message": "\"CHASSIS\" has not been declared as a property alias in relation \"000000000000008665\" of \"@_xxxpb\".",
		"facility": "GF::eai:eproduct",
		"level": "Debug",
		"timeStamp": "2019-02-05T20:52:05.060Z"
	}, {
		"message": "\"INT_EXT\" has not been declared as a property alias in relation \"000000000000008665\" of \"@_xxxpb\".",
		"facility": "GF::eai:eproduct",
		"level": "Debug",
		"timeStamp": "2019-02-05T20:52:05.060Z"
	}, {
		"message": "\"EINHEIT7\" has not been declared as a property alias in relation \"000000000000008666\" of \"@_xxxpb\".",
		"facility": "GF::eai:eproduct",
		"level": "Debug",
		"timeStamp": "2019-02-05T20:52:05.060Z"
	}, {
		"message": "\"EINHEIT8\" has not been declared as a property alias in relation \"000000000000008666\" of \"@_xxxpb\".",
		"facility": "GF::eai:eproduct",
		"level": "Debug",
		"timeStamp": "2019-02-05T20:52:05.060Z"
	}, {
		"message": "\"CHASSIS\" has not been declared as a property alias in relation \"000000000000008666\" of \"@_xxxpb\".",
		"facility": "GF::eai:eproduct",
		"level": "Debug",
		"timeStamp": "2019-02-05T20:52:05.060Z"
	}, {
		"message": "\"INT_EXT\" has not been declared as a property alias in relation \"000000000000008666\" of \"@_xxxpb\".",
		"facility": "GF::eai:eproduct",
		"level": "Debug",
		"timeStamp": "2019-02-05T20:52:05.060Z"
	}, {
		"message": "\"EINHEIT8\" has not been declared as a property alias in relation \"000000000000008667\" of \"@_xxxpb\".",
		"facility": "GF::eai:eproduct",
		"level": "Debug",
		"timeStamp": "2019-02-05T20:52:05.060Z"
	}, {
		"message": "\"EINHEIT9\" has not been declared as a property alias in relation \"000000000000008667\" of \"@_xxxpb\".",
		"facility": "GF::eai:eproduct",
		"level": "Debug",
		"timeStamp": "2019-02-05T20:52:05.060Z"
	}, {
		"message": "\"CHASSIS\" has not been declared as a property alias in relation \"000000000000008667\" of \"@_xxxpb\".",
		"facility": "GF::eai:eproduct",
		"level": "Debug",
		"timeStamp": "2019-02-05T20:52:05.060Z"
	}, {
		"message": "\"INT_EXT\" has not been declared as a property alias in relation \"000000000000008667\" of \"@_xxxpb\".",
		"facility": "GF::eai:eproduct",
		"level": "Debug",
		"timeStamp": "2019-02-05T20:52:05.060Z"
	}, {
		"message": "\"EINHEIT9\" has not been declared as a property alias in relation \"000000000000008668\" of \"@_xxxpb\".",
		"facility": "GF::eai:eproduct",
		"level": "Debug",
		"timeStamp": "2019-02-05T20:52:05.061Z"
	}, {
		"message": "\"EINHEIT10\" has not been declared as a property alias in relation \"000000000000008668\" of \"@_xxxpb\".",
		"facility": "GF::eai:eproduct",
		"level": "Debug",
		"timeStamp": "2019-02-05T20:52:05.061Z"
	}, {
		"message": "\"CHASSIS\" has not been declared as a property alias in relation \"000000000000008668\" of \"@_xxxpb\".",
		"facility": "GF::eai:eproduct",
		"level": "Debug",
		"timeStamp": "2019-02-05T20:52:05.061Z"
	}, {
		"message": "\"INT_EXT\" has not been declared as a property alias in relation \"000000000000008668\" of \"@_xxxpb\".",
		"facility": "GF::eai:eproduct",
		"level": "Debug",
		"timeStamp": "2019-02-05T20:52:05.061Z"
	}, {
		"message": "\"EINHEIT1\" has not been declared as a property alias in relation \"000000000000010151\" of \"@_xxxpb\".",
		"facility": "GF::eai:eproduct",
		"level": "Debug",
		"timeStamp": "2019-02-05T20:52:05.061Z"
	}, {
		"message": "\"EINHEIT2\" has not been declared as a property alias in relation \"000000000000010151\" of \"@_xxxpb\".",
		"facility": "GF::eai:eproduct",
		"level": "Debug",
		"timeStamp": "2019-02-05T20:52:05.061Z"
	}, {
		"message": "\"CHASSIS\" has not been declared as a property alias in relation \"000000000000010151\" of \"@_xxxpb\".",
		"facility": "GF::eai:eproduct",
		"level": "Debug",
		"timeStamp": "2019-02-05T20:52:05.061Z"
	}, {
		"message": "\"INT_EXT\" has not been declared as a property alias in relation \"000000000000010151\" of \"@_xxxpb\".",
		"facility": "GF::eai:eproduct",
		"level": "Debug",
		"timeStamp": "2019-02-05T20:52:05.061Z"
	}, {
		"message": "\"EINHEIT2\" has not been declared as a property alias in relation \"000000000000010147\" of \"@_xxxpb\".",
		"facility": "GF::eai:eproduct",
		"level": "Debug",
		"timeStamp": "2019-02-05T20:52:05.061Z"
	}, {
		"message": "\"EINHEIT3\" has not been declared as a property alias in relation \"000000000000010147\" of \"@_xxxpb\".",
		"facility": "GF::eai:eproduct",
		"level": "Debug",
		"timeStamp": "2019-02-05T20:52:05.061Z"
	}, {
		"message": "\"CHASSIS\" has not been declared as a property alias in relation \"000000000000010147\" of \"@_xxxpb\".",
		"facility": "GF::eai:eproduct",
		"level": "Debug",
		"timeStamp": "2019-02-05T20:52:05.061Z"
	}, {
		"message": "\"INT_EXT\" has not been declared as a property alias in relation \"000000000000010147\" of \"@_xxxpb\".",
		"facility": "GF::eai:eproduct",
		"level": "Debug",
		"timeStamp": "2019-02-05T20:52:05.061Z"
	}, {
		"message": "\"EINHEIT3\" has not been declared as a property alias in relation \"000000000000010148\" of \"@_xxxpb\".",
		"facility": "GF::eai:eproduct",
		"level": "Debug",
		"timeStamp": "2019-02-05T20:52:05.061Z"
	}, {
		"message": "\"EINHEIT4\" has not been declared as a property alias in relation \"000000000000010148\" of \"@_xxxpb\".",
		"facility": "GF::eai:eproduct",
		"level": "Debug",
		"timeStamp": "2019-02-05T20:52:05.061Z"
	}, {
		"message": "\"CHASSIS\" has not been declared as a property alias in relation \"000000000000010148\" of \"@_xxxpb\".",
		"facility": "GF::eai:eproduct",
		"level": "Debug",
		"timeStamp": "2019-02-05T20:52:05.061Z"
	}, {
		"message": "\"INT_EXT\" has not been declared as a property alias in relation \"000000000000010148\" of \"@_xxxpb\".",
		"facility": "GF::eai:eproduct",
		"level": "Debug",
		"timeStamp": "2019-02-05T20:52:05.061Z"
	}, {
		"message": "\"EINHEIT4\" has not been declared as a property alias in relation \"000000000000010149\" of \"@_xxxpb\".",
		"facility": "GF::eai:eproduct",
		"level": "Debug",
		"timeStamp": "2019-02-05T20:52:05.061Z"
	}, {
		"message": "\"EINHEIT5\" has not been declared as a property alias in relation \"000000000000010149\" of \"@_xxxpb\".",
		"facility": "GF::eai:eproduct",
		"level": "Debug",
		"timeStamp": "2019-02-05T20:52:05.061Z"
	}, {
		"message": "\"CHASSIS\" has not been declared as a property alias in relation \"000000000000010149\" of \"@_xxxpb\".",
		"facility": "GF::eai:eproduct",
		"level": "Debug",
		"timeStamp": "2019-02-05T20:52:05.061Z"
	}, {
		"message": "\"INT_EXT\" has not been declared as a property alias in relation \"000000000000010149\" of \"@_xxxpb\".",
		"facility": "GF::eai:eproduct",
		"level": "Debug",
		"timeStamp": "2019-02-05T20:52:05.061Z"
	}, {
		"message": "\"EINHEIT5\" has not been declared as a property alias in relation \"000000000000010159\" of \"@_xxxpb\".",
		"facility": "GF::eai:eproduct",
		"level": "Debug",
		"timeStamp": "2019-02-05T20:52:05.061Z"
	}, {
		"message": "\"EINHEIT6\" has not been declared as a property alias in relation \"000000000000010159\" of \"@_xxxpb\".",
		"facility": "GF::eai:eproduct",
		"level": "Debug",
		"timeStamp": "2019-02-05T20:52:05.061Z"
	}, {
		"message": "\"CHASSIS\" has not been declared as a property alias in relation \"000000000000010159\" of \"@_xxxpb\".",
		"facility": "GF::eai:eproduct",
		"level": "Debug",
		"timeStamp": "2019-02-05T20:52:05.061Z"
	}, {
		"message": "\"INT_EXT\" has not been declared as a property alias in relation \"000000000000010159\" of \"@_xxxpb\".",
		"facility": "GF::eai:eproduct",
		"level": "Debug",
		"timeStamp": "2019-02-05T20:52:05.061Z"
	}, {
		"message": "\"EINHEIT6\" has not been declared as a property alias in relation \"000000000000010156\" of \"@_xxxpb\".",
		"facility": "GF::eai:eproduct",
		"level": "Debug",
		"timeStamp": "2019-02-05T20:52:05.061Z"
	}, {
		"message": "\"EINHEIT7\" has not been declared as a property alias in relation \"000000000000010156\" of \"@_xxxpb\".",
		"facility": "GF::eai:eproduct",
		"level": "Debug",
		"timeStamp": "2019-02-05T20:52:05.061Z"
	}, {
		"message": "\"CHASSIS\" has not been declared as a property alias in relation \"000000000000010156\" of \"@_xxxpb\".",
		"facility": "GF::eai:eproduct",
		"level": "Debug",
		"timeStamp": "2019-02-05T20:52:05.061Z"
	}, {
		"message": "\"INT_EXT\" has not been declared as a property alias in relation \"000000000000010156\" of \"@_xxxpb\".",
		"facility": "GF::eai:eproduct",
		"level": "Debug",
		"timeStamp": "2019-02-05T20:52:05.061Z"
	}, {
		"message": "\"EINHEIT7\" has not been declared as a property alias in relation \"000000000000010157\" of \"@_xxxpb\".",
		"facility": "GF::eai:eproduct",
		"level": "Debug",
		"timeStamp": "2019-02-05T20:52:05.061Z"
	}, {
		"message": "\"EINHEIT8\" has not been declared as a property alias in relation \"000000000000010157\" of \"@_xxxpb\".",
		"facility": "GF::eai:eproduct",
		"level": "Debug",
		"timeStamp": "2019-02-05T20:52:05.061Z"
	}, {
		"message": "\"CHASSIS\" has not been declared as a property alias in relation \"000000000000010157\" of \"@_xxxpb\".",
		"facility": "GF::eai:eproduct",
		"level": "Debug",
		"timeStamp": "2019-02-05T20:52:05.061Z"
	}, {
		"message": "\"INT_EXT\" has not been declared as a property alias in relation \"000000000000010157\" of \"@_xxxpb\".",
		"facility": "GF::eai:eproduct",
		"level": "Debug",
		"timeStamp": "2019-02-05T20:52:05.061Z"
	}, {
		"message": "\"EINHEIT8\" has not been declared as a property alias in relation \"000000000000010158\" of \"@_xxxpb\".",
		"facility": "GF::eai:eproduct",
		"level": "Debug",
		"timeStamp": "2019-02-05T20:52:05.061Z"
	}, {
		"message": "\"EINHEIT9\" has not been declared as a property alias in relation \"000000000000010158\" of \"@_xxxpb\".",
		"facility": "GF::eai:eproduct",
		"level": "Debug",
		"timeStamp": "2019-02-05T20:52:05.061Z"
	}, {
		"message": "\"CHASSIS\" has not been declared as a property alias in relation \"000000000000010158\" of \"@_xxxpb\".",
		"facility": "GF::eai:eproduct",
		"level": "Debug",
		"timeStamp": "2019-02-05T20:52:05.061Z"
	}, {
		"message": "\"INT_EXT\" has not been declared as a property alias in relation \"000000000000010158\" of \"@_xxxpb\".",
		"facility": "GF::eai:eproduct",
		"level": "Debug",
		"timeStamp": "2019-02-05T20:52:05.061Z"
	}, {
		"message": "\"EINHEIT9\" has not been declared as a property alias in relation \"000000000000010152\" of \"@_xxxpb\".",
		"facility": "GF::eai:eproduct",
		"level": "Debug",
		"timeStamp": "2019-02-05T20:52:05.061Z"
	}, {
		"message": "\"EINHEIT10\" has not been declared as a property alias in relation \"000000000000010152\" of \"@_xxxpb\".",
		"facility": "GF::eai:eproduct",
		"level": "Debug",
		"timeStamp": "2019-02-05T20:52:05.061Z"
	}, {
		"message": "\"CHASSIS\" has not been declared as a property alias in relation \"000000000000010152\" of \"@_xxxpb\".",
		"facility": "GF::eai:eproduct",
		"level": "Debug",
		"timeStamp": "2019-02-05T20:52:05.061Z"
	}, {
		"message": "\"INT_EXT\" has not been declared as a property alias in relation \"000000000000010152\" of \"@_xxxpb\".",
		"facility": "GF::eai:eproduct",
		"level": "Debug",
		"timeStamp": "2019-02-05T20:52:05.061Z"
	}, {
		"message": "---------------------------------------- \nFor this NETBOX is a starter- or connection cable required.  \nPlease select it in the area NETLINE!",
		"facility": "GF::afml",
		"level": "Notice",
		"timeStamp": "2019-02-05T20:52:05.092Z"
	}, {
		"message": "\"CHASSIS\" has not been declared as a property alias in relation \"000000000000016625\" of \"@_xxxvtall\".",
		"facility": "GF::eai:eproduct",
		"level": "Debug",
		"timeStamp": "2019-02-05T20:52:12.705Z"
	}, {
		"message": "\"QUERSCHNITT\" has not been declared as a property alias in relation \"000000000000016625\" of \"@_xxxvtall\".",
		"facility": "GF::eai:eproduct",
		"level": "Debug",
		"timeStamp": "2019-02-05T20:52:12.705Z"
	}, {
		"message": "\"CHASSIS\" has not been declared as a property alias in relation \"000000000000016724\" of \"@_xxxvtall\".",
		"facility": "GF::eai:eproduct",
		"level": "Debug",
		"timeStamp": "2019-02-05T20:52:12.705Z"
	}, {
		"message": "\"QUERSCHNITT\" has not been declared as a property alias in relation \"000000000000016724\" of \"@_xxxvtall\".",
		"facility": "GF::eai:eproduct",
		"level": "Debug",
		"timeStamp": "2019-02-05T20:52:12.705Z"
	}, {
		"message": "\"CHASSIS\" has not been declared as a property alias in relation \"000000000000016726\" of \"@_xxxvtall\".",
		"facility": "GF::eai:eproduct",
		"level": "Debug",
		"timeStamp": "2019-02-05T20:52:12.705Z"
	}, {
		"message": "\"QUERSCHNITT\" has not been declared as a property alias in relation \"000000000000016726\" of \"@_xxxvtall\".",
		"facility": "GF::eai:eproduct",
		"level": "Debug",
		"timeStamp": "2019-02-05T20:52:12.705Z"
	}, {
		"message": "\"CHASSIS\" has not been declared as a property alias in relation \"000000000000016728\" of \"@_xxxvtall\".",
		"facility": "GF::eai:eproduct",
		"level": "Debug",
		"timeStamp": "2019-02-05T20:52:12.705Z"
	}, {
		"message": "\"QUERSCHNITT\" has not been declared as a property alias in relation \"000000000000016728\" of \"@_xxxvtall\".",
		"facility": "GF::eai:eproduct",
		"level": "Debug",
		"timeStamp": "2019-02-05T20:52:12.705Z"
	}, {
		"message": "\"CHASSIS\" has not been declared as a property alias in relation \"000000000000016725\" of \"@_xxxvtall\".",
		"facility": "GF::eai:eproduct",
		"level": "Debug",
		"timeStamp": "2019-02-05T20:52:12.705Z"
	}, {
		"message": "\"QUERSCHNITT\" has not been declared as a property alias in relation \"000000000000016725\" of \"@_xxxvtall\".",
		"facility": "GF::eai:eproduct",
		"level": "Debug",
		"timeStamp": "2019-02-05T20:52:12.705Z"
	}, {
		"message": "\"CHASSIS\" has not been declared as a property alias in relation \"000000000000016727\" of \"@_xxxvtall\".",
		"facility": "GF::eai:eproduct",
		"level": "Debug",
		"timeStamp": "2019-02-05T20:52:12.705Z"
	}, {
		"message": "\"QUERSCHNITT\" has not been declared as a property alias in relation \"000000000000016727\" of \"@_xxxvtall\".",
		"facility": "GF::eai:eproduct",
		"level": "Debug",
		"timeStamp": "2019-02-05T20:52:12.705Z"
	}, {
		"message": "\"CHASSIS\" has not been declared as a property alias in relation \"000000000000016729\" of \"@_xxxvtall\".",
		"facility": "GF::eai:eproduct",
		"level": "Debug",
		"timeStamp": "2019-02-05T20:52:12.705Z"
	}, {
		"message": "\"QUERSCHNITT\" has not been declared as a property alias in relation \"000000000000016729\" of \"@_xxxvtall\".",
		"facility": "GF::eai:eproduct",
		"level": "Debug",
		"timeStamp": "2019-02-05T20:52:12.705Z"
	}, {
		"message": "\"CHASSIS\" has not been declared as a property alias in relation \"000000000000016730\" of \"@_xxxvtall\".",
		"facility": "GF::eai:eproduct",
		"level": "Debug",
		"timeStamp": "2019-02-05T20:52:12.705Z"
	}, {
		"message": "\"QUERSCHNITT\" has not been declared as a property alias in relation \"000000000000016730\" of \"@_xxxvtall\".",
		"facility": "GF::eai:eproduct",
		"level": "Debug",
		"timeStamp": "2019-02-05T20:52:12.705Z"
	}, {
		"message": "\"CHASSIS\" has not been declared as a property alias in relation \"000000000000016741\" of \"@_xxxvtall\".",
		"facility": "GF::eai:eproduct",
		"level": "Debug",
		"timeStamp": "2019-02-05T20:52:12.705Z"
	}, {
		"message": "\"QUERSCHNITT\" has not been declared as a property alias in relation \"000000000000016741\" of \"@_xxxvtall\".",
		"facility": "GF::eai:eproduct",
		"level": "Debug",
		"timeStamp": "2019-02-05T20:52:12.705Z"
	}, {
		"message": "\"CHASSIS\" has not been declared as a property alias in relation \"000000000000016742\" of \"@_xxxvtall\".",
		"facility": "GF::eai:eproduct",
		"level": "Debug",
		"timeStamp": "2019-02-05T20:52:12.705Z"
	}, {
		"message": "\"QUERSCHNITT\" has not been declared as a property alias in relation \"000000000000016742\" of \"@_xxxvtall\".",
		"facility": "GF::eai:eproduct",
		"level": "Debug",
		"timeStamp": "2019-02-05T20:52:12.705Z"
	}, {
		"message": "\"CHASSIS\" has not been declared as a property alias in relation \"000000000000016744\" of \"@_xxxvtall\".",
		"facility": "GF::eai:eproduct",
		"level": "Debug",
		"timeStamp": "2019-02-05T20:52:12.705Z"
	}, {
		"message": "\"QUERSCHNITT\" has not been declared as a property alias in relation \"000000000000016744\" of \"@_xxxvtall\".",
		"facility": "GF::eai:eproduct",
		"level": "Debug",
		"timeStamp": "2019-02-05T20:52:12.705Z"
	}, {
		"message": "\"CHASSIS\" has not been declared as a property alias in relation \"000000000000016746\" of \"@_xxxvtall\".",
		"facility": "GF::eai:eproduct",
		"level": "Debug",
		"timeStamp": "2019-02-05T20:52:12.705Z"
	}, {
		"message": "\"QUERSCHNITT\" has not been declared as a property alias in relation \"000000000000016746\" of \"@_xxxvtall\".",
		"facility": "GF::eai:eproduct",
		"level": "Debug",
		"timeStamp": "2019-02-05T20:52:12.705Z"
	}, {
		"message": "\"CHASSIS\" has not been declared as a property alias in relation \"000000000000016743\" of \"@_xxxvtall\".",
		"facility": "GF::eai:eproduct",
		"level": "Debug",
		"timeStamp": "2019-02-05T20:52:12.705Z"
	}, {
		"message": "\"QUERSCHNITT\" has not been declared as a property alias in relation \"000000000000016743\" of \"@_xxxvtall\".",
		"facility": "GF::eai:eproduct",
		"level": "Debug",
		"timeStamp": "2019-02-05T20:52:12.705Z"
	}, {
		"message": "\"CHASSIS\" has not been declared as a property alias in relation \"000000000000016745\" of \"@_xxxvtall\".",
		"facility": "GF::eai:eproduct",
		"level": "Debug",
		"timeStamp": "2019-02-05T20:52:12.705Z"
	}, {
		"message": "\"QUERSCHNITT\" has not been declared as a property alias in relation \"000000000000016745\" of \"@_xxxvtall\".",
		"facility": "GF::eai:eproduct",
		"level": "Debug",
		"timeStamp": "2019-02-05T20:52:12.705Z"
	}, {
		"message": "\"CHASSIS\" has not been declared as a property alias in relation \"000000000000016747\" of \"@_xxxvtall\".",
		"facility": "GF::eai:eproduct",
		"level": "Debug",
		"timeStamp": "2019-02-05T20:52:12.705Z"
	}, {
		"message": "\"QUERSCHNITT\" has not been declared as a property alias in relation \"000000000000016747\" of \"@_xxxvtall\".",
		"facility": "GF::eai:eproduct",
		"level": "Debug",
		"timeStamp": "2019-02-05T20:52:12.705Z"
	}, {
		"message": "\"CHASSIS\" has not been declared as a property alias in relation \"000000000000016748\" of \"@_xxxvtall\".",
		"facility": "GF::eai:eproduct",
		"level": "Debug",
		"timeStamp": "2019-02-05T20:52:12.705Z"
	}, {
		"message": "\"QUERSCHNITT\" has not been declared as a property alias in relation \"000000000000016748\" of \"@_xxxvtall\".",
		"facility": "GF::eai:eproduct",
		"level": "Debug",
		"timeStamp": "2019-02-05T20:52:12.705Z"
	}, {
		"message": "\"CHASSIS\" has not been declared as a property alias in relation \"000000000000016735\" of \"@_xxxvtall\".",
		"facility": "GF::eai:eproduct",
		"level": "Debug",
		"timeStamp": "2019-02-05T20:52:12.705Z"
	}, {
		"message": "\"CHASSIS\" has not been declared as a property alias in relation \"000000000000016756\" of \"@_xxxvtall\".",
		"facility": "GF::eai:eproduct",
		"level": "Debug",
		"timeStamp": "2019-02-05T20:52:12.705Z"
	}, {
		"message": "\"CHASSIS\" has not been declared as a property alias in relation \"000000000000016758\" of \"@_xxxvtall\".",
		"facility": "GF::eai:eproduct",
		"level": "Debug",
		"timeStamp": "2019-02-05T20:52:12.705Z"
	}, {
		"message": "\"CHASSIS\" has not been declared as a property alias in relation \"000000000000016760\" of \"@_xxxvtall\".",
		"facility": "GF::eai:eproduct",
		"level": "Debug",
		"timeStamp": "2019-02-05T20:52:12.705Z"
	}, {
		"message": "\"CHASSIS\" has not been declared as a property alias in relation \"000000000000016762\" of \"@_xxxvtall\".",
		"facility": "GF::eai:eproduct",
		"level": "Debug",
		"timeStamp": "2019-02-05T20:52:12.705Z"
	}, {
		"message": "\"CHASSIS\" has not been declared as a property alias in relation \"000000000000016764\" of \"@_xxxvtall\".",
		"facility": "GF::eai:eproduct",
		"level": "Debug",
		"timeStamp": "2019-02-05T20:52:12.705Z"
	}, {
		"message": "\"CHASSIS\" has not been declared as a property alias in relation \"000000000000016757\" of \"@_xxxvtall\".",
		"facility": "GF::eai:eproduct",
		"level": "Debug",
		"timeStamp": "2019-02-05T20:52:12.705Z"
	}, {
		"message": "\"CHASSIS\" has not been declared as a property alias in relation \"000000000000016759\" of \"@_xxxvtall\".",
		"facility": "GF::eai:eproduct",
		"level": "Debug",
		"timeStamp": "2019-02-05T20:52:12.705Z"
	}, {
		"message": "\"CHASSIS\" has not been declared as a property alias in relation \"000000000000016761\" of \"@_xxxvtall\".",
		"facility": "GF::eai:eproduct",
		"level": "Debug",
		"timeStamp": "2019-02-05T20:52:12.705Z"
	}, {
		"message": "\"CHASSIS\" has not been declared as a property alias in relation \"000000000000016763\" of \"@_xxxvtall\".",
		"facility": "GF::eai:eproduct",
		"level": "Debug",
		"timeStamp": "2019-02-05T20:52:12.705Z"
	}, {
		"message": "\"CHASSIS\" has not been declared as a property alias in relation \"000000000000016765\" of \"@_xxxvtall\".",
		"facility": "GF::eai:eproduct",
		"level": "Debug",
		"timeStamp": "2019-02-05T20:52:12.705Z"
	}, {
		"message": "\"CHASSIS\" has not been declared as a property alias in relation \"000000000000016766\" of \"@_xxxvtall\".",
		"facility": "GF::eai:eproduct",
		"level": "Debug",
		"timeStamp": "2019-02-05T20:52:12.705Z"
	}, {
		"message": "---------------------------------------- \nThe configuration of the distribution box is not checked by pCon, \nplease consult in case of doubt!",
		"facility": "GF::afml",
		"level": "Notice",
		"timeStamp": "2019-02-07T20:52:12.709Z"
	}],
	"discarded": 0,
	"suppressed": 0
}
